// class version 52.0 (52)
// access flags 0x31
public final class okhttp3/OkHttpClient$Builder {

  // compiled from: OkHttpClient.kt
  // debug info: SMAP
OkHttpClient.kt
Kotlin
*S Kotlin
*F
+ 1 OkHttpClient.kt
okhttp3/OkHttpClient$Builder
+ 2 fake.kt
kotlin/jvm/internal/FakeKt
*L
1#1,1079:1
1#2:1080
*E


  @Lkotlin/Metadata;(mv={1, 8, 0}, k=1, xi=48, d1={"\u0000\u00f8\u0001\n\u0002\u0018\u0002\n\u0002\u0010\u0000\n\u0000\n\u0002\u0018\u0002\n\u0002\u0008\u0003\n\u0002\u0018\u0002\n\u0002\u0008\u0005\n\u0002\u0018\u0002\n\u0002\u0008\u0005\n\u0002\u0010\u0008\n\u0002\u0008\u0005\n\u0002\u0018\u0002\n\u0002\u0008\u0005\n\u0002\u0018\u0002\n\u0002\u0008\u0008\n\u0002\u0018\u0002\n\u0002\u0008\u0005\n\u0002\u0010 \n\u0002\u0018\u0002\n\u0002\u0008\u0005\n\u0002\u0018\u0002\n\u0002\u0008\u0005\n\u0002\u0018\u0002\n\u0002\u0008\u0005\n\u0002\u0018\u0002\n\u0002\u0008\u0005\n\u0002\u0018\u0002\n\u0002\u0008\u0005\n\u0002\u0010\u000b\n\u0002\u0008\u0008\n\u0002\u0018\u0002\n\u0002\u0008\u0005\n\u0002\u0010!\n\u0002\u0018\u0002\n\u0002\u0008\u0002\n\u0002\u0010\u0009\n\u0002\u0008\n\n\u0002\u0018\u0002\n\u0002\u0008\u0003\n\u0002\u0018\u0002\n\u0002\u0008\u0008\n\u0002\u0018\u0002\n\u0002\u0008\u000b\n\u0002\u0018\u0002\n\u0002\u0008\u0005\n\u0002\u0018\u0002\n\u0002\u0008\u0005\n\u0002\u0018\u0002\n\u0002\u0008\u0008\n\u0002\u0018\u0002\n\u0002\u0008\u0006\n\u0002\u0018\u0002\n\u0002\u0018\u0002\n\u0002\u0018\u0002\n\u0002\u0008\u0002\n\u0002\u0018\u0002\n\u0002\u0008\u0006\n\u0002\u0018\u0002\n\u0002\u0008\u0002\n\u0002\u0018\u0002\n\u0000\n\u0002\u0018\u0002\n\u0002\u0008\u0006\u0018\u00002\u00020\u0001B\u000f\u0008\u0010\u0012\u0006\u0010\u0002\u001a\u00020\u0003\u00a2\u0006\u0002\u0010\u0004B\u0005\u00a2\u0006\u0002\u0010\u0005J?\u0010\u009e\u0001\u001a\u00020\u00002*\u0008\u0004\u0010\u009f\u0001\u001a#\u0012\u0017\u0012\u00150\u00a1\u0001\u00a2\u0006\u000f\u0008\u00a2\u0001\u0012\n\u0008\u00a3\u0001\u0012\u0005\u0008\u0008(\u00a4\u0001\u0012\u0005\u0012\u00030\u00a5\u00010\u00a0\u0001H\u0087\u0008\u00f8\u0001\u0000\u00a2\u0006\u0003\u0008\u00a6\u0001J\u0010\u0010\u009e\u0001\u001a\u00020\u00002\u0007\u0010\u00a7\u0001\u001a\u00020]J?\u0010\u00a8\u0001\u001a\u00020\u00002*\u0008\u0004\u0010\u009f\u0001\u001a#\u0012\u0017\u0012\u00150\u00a1\u0001\u00a2\u0006\u000f\u0008\u00a2\u0001\u0012\n\u0008\u00a3\u0001\u0012\u0005\u0008\u0008(\u00a4\u0001\u0012\u0005\u0012\u00030\u00a5\u00010\u00a0\u0001H\u0087\u0008\u00f8\u0001\u0000\u00a2\u0006\u0003\u0008\u00a9\u0001J\u0010\u0010\u00a8\u0001\u001a\u00020\u00002\u0007\u0010\u00a7\u0001\u001a\u00020]J\u000e\u0010\u0006\u001a\u00020\u00002\u0006\u0010\u0006\u001a\u00020\u0007J\u0007\u0010\u00aa\u0001\u001a\u00020\u0003J\u0010\u0010\u000c\u001a\u00020\u00002\u0008\u0010\u000c\u001a\u0004\u0018\u00010\rJ\u0012\u0010\u0012\u001a\u00020\u00002\u0008\u0010\u00ab\u0001\u001a\u00030\u00ac\u0001H\u0007J\u0019\u0010\u0012\u001a\u00020\u00002\u0007\u0010\u00ad\u0001\u001a\u00020`2\u0008\u0010\u00ae\u0001\u001a\u00030\u00af\u0001J\u000e\u0010\u001e\u001a\u00020\u00002\u0006\u0010\u001e\u001a\u00020\u001fJ\u0012\u0010$\u001a\u00020\u00002\u0008\u0010\u00ab\u0001\u001a\u00030\u00ac\u0001H\u0007J\u0019\u0010$\u001a\u00020\u00002\u0007\u0010\u00ad\u0001\u001a\u00020`2\u0008\u0010\u00ae\u0001\u001a\u00030\u00af\u0001J\u000e\u0010'\u001a\u00020\u00002\u0006\u0010'\u001a\u00020(J\u0014\u0010-\u001a\u00020\u00002\u000c\u0010-\u001a\u0008\u0012\u0004\u0012\u00020/0.J\u000e\u00104\u001a\u00020\u00002\u0006\u00104\u001a\u000205J\u000e\u0010:\u001a\u00020\u00002\u0006\u0010:\u001a\u00020;J\u000e\u0010@\u001a\u00020\u00002\u0006\u0010@\u001a\u00020AJ\u0011\u0010\u00b0\u0001\u001a\u00020\u00002\u0008\u0010\u00b0\u0001\u001a\u00030\u00b1\u0001J\u000e\u0010F\u001a\u00020\u00002\u0006\u0010F\u001a\u00020GJ\u000e\u0010L\u001a\u00020\u00002\u0006\u0010L\u001a\u00020MJ\u000f\u0010R\u001a\u00020\u00002\u0007\u0010\u00b2\u0001\u001a\u00020MJ\u000e\u0010U\u001a\u00020\u00002\u0006\u0010U\u001a\u00020VJ\u000c\u0010[\u001a\u0008\u0012\u0004\u0012\u00020]0\\J\u000f\u0010_\u001a\u00020\u00002\u0007\u0010\u00b3\u0001\u001a\u00020`J\u000c\u0010e\u001a\u0008\u0012\u0004\u0012\u00020]0\\J\u0012\u0010g\u001a\u00020\u00002\u0008\u0010\u00ab\u0001\u001a\u00030\u00ac\u0001H\u0007J\u0019\u0010g\u001a\u00020\u00002\u0007\u0010\u00b4\u0001\u001a\u00020`2\u0008\u0010\u00ae\u0001\u001a\u00030\u00af\u0001J\u0014\u0010j\u001a\u00020\u00002\u000c\u0010j\u001a\u0008\u0012\u0004\u0012\u00020k0.J\u0010\u0010n\u001a\u00020\u00002\u0008\u0010n\u001a\u0004\u0018\u00010oJ\u000e\u0010t\u001a\u00020\u00002\u0006\u0010t\u001a\u00020\u0007J\u000e\u0010w\u001a\u00020\u00002\u0006\u0010w\u001a\u00020xJ\u0012\u0010}\u001a\u00020\u00002\u0008\u0010\u00ab\u0001\u001a\u00030\u00ac\u0001H\u0007J\u0019\u0010}\u001a\u00020\u00002\u0007\u0010\u00ad\u0001\u001a\u00020`2\u0008\u0010\u00ae\u0001\u001a\u00030\u00af\u0001J\u0010\u0010\u0080\u0001\u001a\u00020\u00002\u0007\u0010\u0080\u0001\u001a\u00020MJ\u0011\u0010\u0089\u0001\u001a\u00020\u00002\u0008\u0010\u0089\u0001\u001a\u00030\u008a\u0001J\u0013\u0010\u00b5\u0001\u001a\u00020\u00002\u0008\u0010\u00b5\u0001\u001a\u00030\u0090\u0001H\u0007J\u001b\u0010\u00b5\u0001\u001a\u00020\u00002\u0008\u0010\u00b5\u0001\u001a\u00030\u0090\u00012\u0008\u0010\u00b6\u0001\u001a\u00030\u0099\u0001J\u0013\u0010\u0095\u0001\u001a\u00020\u00002\u0008\u0010\u00ab\u0001\u001a\u00030\u00ac\u0001H\u0007J\u001a\u0010\u0095\u0001\u001a\u00020\u00002\u0007\u0010\u00ad\u0001\u001a\u00020`2\u0008\u0010\u00ae\u0001\u001a\u00030\u00af\u0001R\u001a\u0010\u0006\u001a\u00020\u0007X\u0080\u000e\u00a2\u0006\u000e\n\u0000\u001a\u0004\u0008\u0008\u0010\u0009\"\u0004\u0008\n\u0010\u000bR\u001c\u0010\u000c\u001a\u0004\u0018\u00010\rX\u0080\u000e\u00a2\u0006\u000e\n\u0000\u001a\u0004\u0008\u000e\u0010\u000f\"\u0004\u0008\u0010\u0010\u0011R\u001a\u0010\u0012\u001a\u00020\u0013X\u0080\u000e\u00a2\u0006\u000e\n\u0000\u001a\u0004\u0008\u0014\u0010\u0015\"\u0004\u0008\u0016\u0010\u0017R\u001c\u0010\u0018\u001a\u0004\u0018\u00010\u0019X\u0080\u000e\u00a2\u0006\u000e\n\u0000\u001a\u0004\u0008\u001a\u0010\u001b\"\u0004\u0008\u001c\u0010\u001dR\u001a\u0010\u001e\u001a\u00020\u001fX\u0080\u000e\u00a2\u0006\u000e\n\u0000\u001a\u0004\u0008 \u0010!\"\u0004\u0008\"\u0010#R\u001a\u0010$\u001a\u00020\u0013X\u0080\u000e\u00a2\u0006\u000e\n\u0000\u001a\u0004\u0008%\u0010\u0015\"\u0004\u0008&\u0010\u0017R\u001a\u0010'\u001a\u00020(X\u0080\u000e\u00a2\u0006\u000e\n\u0000\u001a\u0004\u0008)\u0010*\"\u0004\u0008+\u0010,R \u0010-\u001a\u0008\u0012\u0004\u0012\u00020/0.X\u0080\u000e\u00a2\u0006\u000e\n\u0000\u001a\u0004\u00080\u00101\"\u0004\u00082\u00103R\u001a\u00104\u001a\u000205X\u0080\u000e\u00a2\u0006\u000e\n\u0000\u001a\u0004\u00086\u00107\"\u0004\u00088\u00109R\u001a\u0010:\u001a\u00020;X\u0080\u000e\u00a2\u0006\u000e\n\u0000\u001a\u0004\u0008<\u0010=\"\u0004\u0008>\u0010?R\u001a\u0010@\u001a\u00020AX\u0080\u000e\u00a2\u0006\u000e\n\u0000\u001a\u0004\u0008B\u0010C\"\u0004\u0008D\u0010ER\u001a\u0010F\u001a\u00020GX\u0080\u000e\u00a2\u0006\u000e\n\u0000\u001a\u0004\u0008H\u0010I\"\u0004\u0008J\u0010KR\u001a\u0010L\u001a\u00020MX\u0080\u000e\u00a2\u0006\u000e\n\u0000\u001a\u0004\u0008N\u0010O\"\u0004\u0008P\u0010QR\u001a\u0010R\u001a\u00020MX\u0080\u000e\u00a2\u0006\u000e\n\u0000\u001a\u0004\u0008S\u0010O\"\u0004\u0008T\u0010QR\u001a\u0010U\u001a\u00020VX\u0080\u000e\u00a2\u0006\u000e\n\u0000\u001a\u0004\u0008W\u0010X\"\u0004\u0008Y\u0010ZR\u001a\u0010[\u001a\u0008\u0012\u0004\u0012\u00020]0\\X\u0080\u0004\u00a2\u0006\u0008\n\u0000\u001a\u0004\u0008^\u00101R\u001a\u0010_\u001a\u00020`X\u0080\u000e\u00a2\u0006\u000e\n\u0000\u001a\u0004\u0008a\u0010b\"\u0004\u0008c\u0010dR\u001a\u0010e\u001a\u0008\u0012\u0004\u0012\u00020]0\\X\u0080\u0004\u00a2\u0006\u0008\n\u0000\u001a\u0004\u0008f\u00101R\u001a\u0010g\u001a\u00020\u0013X\u0080\u000e\u00a2\u0006\u000e\n\u0000\u001a\u0004\u0008h\u0010\u0015\"\u0004\u0008i\u0010\u0017R \u0010j\u001a\u0008\u0012\u0004\u0012\u00020k0.X\u0080\u000e\u00a2\u0006\u000e\n\u0000\u001a\u0004\u0008l\u00101\"\u0004\u0008m\u00103R\u001c\u0010n\u001a\u0004\u0018\u00010oX\u0080\u000e\u00a2\u0006\u000e\n\u0000\u001a\u0004\u0008p\u0010q\"\u0004\u0008r\u0010sR\u001a\u0010t\u001a\u00020\u0007X\u0080\u000e\u00a2\u0006\u000e\n\u0000\u001a\u0004\u0008u\u0010\u0009\"\u0004\u0008v\u0010\u000bR\u001c\u0010w\u001a\u0004\u0018\u00010xX\u0080\u000e\u00a2\u0006\u000e\n\u0000\u001a\u0004\u0008y\u0010z\"\u0004\u0008{\u0010|R\u001a\u0010}\u001a\u00020\u0013X\u0080\u000e\u00a2\u0006\u000e\n\u0000\u001a\u0004\u0008~\u0010\u0015\"\u0004\u0008\u0010\u0017R\u001d\u0010\u0080\u0001\u001a\u00020MX\u0080\u000e\u00a2\u0006\u0010\n\u0000\u001a\u0005\u0008\u0081\u0001\u0010O\"\u0005\u0008\u0082\u0001\u0010QR\"\u0010\u0083\u0001\u001a\u0005\u0018\u00010\u0084\u0001X\u0080\u000e\u00a2\u0006\u0012\n\u0000\u001a\u0006\u0008\u0085\u0001\u0010\u0086\u0001\"\u0006\u0008\u0087\u0001\u0010\u0088\u0001R \u0010\u0089\u0001\u001a\u00030\u008a\u0001X\u0080\u000e\u00a2\u0006\u0012\n\u0000\u001a\u0006\u0008\u008b\u0001\u0010\u008c\u0001\"\u0006\u0008\u008d\u0001\u0010\u008e\u0001R\"\u0010\u008f\u0001\u001a\u0005\u0018\u00010\u0090\u0001X\u0080\u000e\u00a2\u0006\u0012\n\u0000\u001a\u0006\u0008\u0091\u0001\u0010\u0092\u0001\"\u0006\u0008\u0093\u0001\u0010\u0094\u0001R\u001d\u0010\u0095\u0001\u001a\u00020\u0013X\u0080\u000e\u00a2\u0006\u0010\n\u0000\u001a\u0005\u0008\u0096\u0001\u0010\u0015\"\u0005\u0008\u0097\u0001\u0010\u0017R\"\u0010\u0098\u0001\u001a\u0005\u0018\u00010\u0099\u0001X\u0080\u000e\u00a2\u0006\u0012\n\u0000\u001a\u0006\u0008\u009a\u0001\u0010\u009b\u0001\"\u0006\u0008\u009c\u0001\u0010\u009d\u0001\u0082\u0002\u0007\n\u0005\u0008\u009920\u0001\u00a8\u0006\u00b7\u0001"}, d2={"Lokhttp3/OkHttpClient$Builder;", "", "okHttpClient", "Lokhttp3/OkHttpClient;", "(Lokhttp3/OkHttpClient;)V", "()V", "authenticator", "Lokhttp3/Authenticator;", "getAuthenticator$okhttp", "()Lokhttp3/Authenticator;", "setAuthenticator$okhttp", "(Lokhttp3/Authenticator;)V", "cache", "Lokhttp3/Cache;", "getCache$okhttp", "()Lokhttp3/Cache;", "setCache$okhttp", "(Lokhttp3/Cache;)V", "callTimeout", "", "getCallTimeout$okhttp", "()I", "setCallTimeout$okhttp", "(I)V", "certificateChainCleaner", "Lokhttp3/internal/tls/CertificateChainCleaner;", "getCertificateChainCleaner$okhttp", "()Lokhttp3/internal/tls/CertificateChainCleaner;", "setCertificateChainCleaner$okhttp", "(Lokhttp3/internal/tls/CertificateChainCleaner;)V", "certificatePinner", "Lokhttp3/CertificatePinner;", "getCertificatePinner$okhttp", "()Lokhttp3/CertificatePinner;", "setCertificatePinner$okhttp", "(Lokhttp3/CertificatePinner;)V", "connectTimeout", "getConnectTimeout$okhttp", "setConnectTimeout$okhttp", "connectionPool", "Lokhttp3/ConnectionPool;", "getConnectionPool$okhttp", "()Lokhttp3/ConnectionPool;", "setConnectionPool$okhttp", "(Lokhttp3/ConnectionPool;)V", "connectionSpecs", "", "Lokhttp3/ConnectionSpec;", "getConnectionSpecs$okhttp", "()Ljava/util/List;", "setConnectionSpecs$okhttp", "(Ljava/util/List;)V", "cookieJar", "Lokhttp3/CookieJar;", "getCookieJar$okhttp", "()Lokhttp3/CookieJar;", "setCookieJar$okhttp", "(Lokhttp3/CookieJar;)V", "dispatcher", "Lokhttp3/Dispatcher;", "getDispatcher$okhttp", "()Lokhttp3/Dispatcher;", "setDispatcher$okhttp", "(Lokhttp3/Dispatcher;)V", "dns", "Lokhttp3/Dns;", "getDns$okhttp", "()Lokhttp3/Dns;", "setDns$okhttp", "(Lokhttp3/Dns;)V", "eventListenerFactory", "Lokhttp3/EventListener$Factory;", "getEventListenerFactory$okhttp", "()Lokhttp3/EventListener$Factory;", "setEventListenerFactory$okhttp", "(Lokhttp3/EventListener$Factory;)V", "followRedirects", "", "getFollowRedirects$okhttp", "()Z", "setFollowRedirects$okhttp", "(Z)V", "followSslRedirects", "getFollowSslRedirects$okhttp", "setFollowSslRedirects$okhttp", "hostnameVerifier", "Ljavax/net/ssl/HostnameVerifier;", "getHostnameVerifier$okhttp", "()Ljavax/net/ssl/HostnameVerifier;", "setHostnameVerifier$okhttp", "(Ljavax/net/ssl/HostnameVerifier;)V", "interceptors", "", "Lokhttp3/Interceptor;", "getInterceptors$okhttp", "minWebSocketMessageToCompress", "", "getMinWebSocketMessageToCompress$okhttp", "()J", "setMinWebSocketMessageToCompress$okhttp", "(J)V", "networkInterceptors", "getNetworkInterceptors$okhttp", "pingInterval", "getPingInterval$okhttp", "setPingInterval$okhttp", "protocols", "Lokhttp3/Protocol;", "getProtocols$okhttp", "setProtocols$okhttp", "proxy", "Ljava/net/Proxy;", "getProxy$okhttp", "()Ljava/net/Proxy;", "setProxy$okhttp", "(Ljava/net/Proxy;)V", "proxyAuthenticator", "getProxyAuthenticator$okhttp", "setProxyAuthenticator$okhttp", "proxySelector", "Ljava/net/ProxySelector;", "getProxySelector$okhttp", "()Ljava/net/ProxySelector;", "setProxySelector$okhttp", "(Ljava/net/ProxySelector;)V", "readTimeout", "getReadTimeout$okhttp", "setReadTimeout$okhttp", "retryOnConnectionFailure", "getRetryOnConnectionFailure$okhttp", "setRetryOnConnectionFailure$okhttp", "routeDatabase", "Lokhttp3/internal/connection/RouteDatabase;", "getRouteDatabase$okhttp", "()Lokhttp3/internal/connection/RouteDatabase;", "setRouteDatabase$okhttp", "(Lokhttp3/internal/connection/RouteDatabase;)V", "socketFactory", "Ljavax/net/SocketFactory;", "getSocketFactory$okhttp", "()Ljavax/net/SocketFactory;", "setSocketFactory$okhttp", "(Ljavax/net/SocketFactory;)V", "sslSocketFactoryOrNull", "Ljavax/net/ssl/SSLSocketFactory;", "getSslSocketFactoryOrNull$okhttp", "()Ljavax/net/ssl/SSLSocketFactory;", "setSslSocketFactoryOrNull$okhttp", "(Ljavax/net/ssl/SSLSocketFactory;)V", "writeTimeout", "getWriteTimeout$okhttp", "setWriteTimeout$okhttp", "x509TrustManagerOrNull", "Ljavax/net/ssl/X509TrustManager;", "getX509TrustManagerOrNull$okhttp", "()Ljavax/net/ssl/X509TrustManager;", "setX509TrustManagerOrNull$okhttp", "(Ljavax/net/ssl/X509TrustManager;)V", "addInterceptor", "block", "Lkotlin/Function1;", "Lokhttp3/Interceptor$Chain;", "Lkotlin/ParameterName;", "name", "chain", "Lokhttp3/Response;", "-addInterceptor", "interceptor", "addNetworkInterceptor", "-addNetworkInterceptor", "build", "duration", "Ljava/time/Duration;", "timeout", "unit", "Ljava/util/concurrent/TimeUnit;", "eventListener", "Lokhttp3/EventListener;", "followProtocolRedirects", "bytes", "interval", "sslSocketFactory", "trustManager", "okhttp"})

  @Lkotlin/jvm/internal/SourceDebugExtension;(value={"SMAP\nOkHttpClient.kt\nKotlin\n*S Kotlin\n*F\n+ 1 OkHttpClient.kt\nokhttp3/OkHttpClient$Builder\n+ 2 fake.kt\nkotlin/jvm/internal/FakeKt\n*L\n1#1,1079:1\n1#2:1080\n*E\n"}) // invisible
  // access flags 0x609
  public static abstract INNERCLASS okhttp3/EventListener$Factory okhttp3/EventListener Factory
  // access flags 0x609
  public static abstract INNERCLASS okhttp3/Interceptor$Chain okhttp3/Interceptor Chain
  // access flags 0x19
  public final static INNERCLASS okhttp3/OkHttpClient$Builder okhttp3/OkHttpClient Builder
  // access flags 0x19
  public final static INNERCLASS okhttp3/OkHttpClient$Builder$addInterceptor$2 null null
  // access flags 0x19
  public final static INNERCLASS okhttp3/OkHttpClient$Builder$addNetworkInterceptor$2 null null
  // access flags 0x19
  public final static INNERCLASS okhttp3/OkHttpClient$Companion okhttp3/OkHttpClient Companion
  // access flags 0x19
  public final static INNERCLASS okhttp3/internal/platform/Platform$Companion okhttp3/internal/platform/Platform Companion
  // access flags 0x19
  public final static INNERCLASS okhttp3/internal/tls/CertificateChainCleaner$Companion okhttp3/internal/tls/CertificateChainCleaner Companion

  // access flags 0x2
  private Lokhttp3/Dispatcher; dispatcher
  @Lorg/jetbrains/annotations/NotNull;() // invisible

  // access flags 0x2
  private Lokhttp3/ConnectionPool; connectionPool
  @Lorg/jetbrains/annotations/NotNull;() // invisible

  // access flags 0x12
  // signature Ljava/util/List<Lokhttp3/Interceptor;>;
  // declaration: interceptors extends java.util.List<okhttp3.Interceptor>
  private final Ljava/util/List; interceptors
  @Lorg/jetbrains/annotations/NotNull;() // invisible

  // access flags 0x12
  // signature Ljava/util/List<Lokhttp3/Interceptor;>;
  // declaration: networkInterceptors extends java.util.List<okhttp3.Interceptor>
  private final Ljava/util/List; networkInterceptors
  @Lorg/jetbrains/annotations/NotNull;() // invisible

  // access flags 0x2
  private Lokhttp3/EventListener$Factory; eventListenerFactory
  @Lorg/jetbrains/annotations/NotNull;() // invisible

  // access flags 0x2
  private Z retryOnConnectionFailure

  // access flags 0x2
  private Lokhttp3/Authenticator; authenticator
  @Lorg/jetbrains/annotations/NotNull;() // invisible

  // access flags 0x2
  private Z followRedirects

  // access flags 0x2
  private Z followSslRedirects

  // access flags 0x2
  private Lokhttp3/CookieJar; cookieJar
  @Lorg/jetbrains/annotations/NotNull;() // invisible

  // access flags 0x2
  private Lokhttp3/Cache; cache
  @Lorg/jetbrains/annotations/Nullable;() // invisible

  // access flags 0x2
  private Lokhttp3/Dns; dns
  @Lorg/jetbrains/annotations/NotNull;() // invisible

  // access flags 0x2
  private Ljava/net/Proxy; proxy
  @Lorg/jetbrains/annotations/Nullable;() // invisible

  // access flags 0x2
  private Ljava/net/ProxySelector; proxySelector
  @Lorg/jetbrains/annotations/Nullable;() // invisible

  // access flags 0x2
  private Lokhttp3/Authenticator; proxyAuthenticator
  @Lorg/jetbrains/annotations/NotNull;() // invisible

  // access flags 0x2
  private Ljavax/net/SocketFactory; socketFactory
  @Lorg/jetbrains/annotations/NotNull;() // invisible

  // access flags 0x2
  private Ljavax/net/ssl/SSLSocketFactory; sslSocketFactoryOrNull
  @Lorg/jetbrains/annotations/Nullable;() // invisible

  // access flags 0x2
  private Ljavax/net/ssl/X509TrustManager; x509TrustManagerOrNull
  @Lorg/jetbrains/annotations/Nullable;() // invisible

  // access flags 0x2
  // signature Ljava/util/List<Lokhttp3/ConnectionSpec;>;
  // declaration: connectionSpecs extends java.util.List<okhttp3.ConnectionSpec>
  private Ljava/util/List; connectionSpecs
  @Lorg/jetbrains/annotations/NotNull;() // invisible

  // access flags 0x2
  // signature Ljava/util/List<+Lokhttp3/Protocol;>;
  // declaration: protocols extends java.util.List<? extends okhttp3.Protocol>
  private Ljava/util/List; protocols
  @Lorg/jetbrains/annotations/NotNull;() // invisible

  // access flags 0x2
  private Ljavax/net/ssl/HostnameVerifier; hostnameVerifier
  @Lorg/jetbrains/annotations/NotNull;() // invisible

  // access flags 0x2
  private Lokhttp3/CertificatePinner; certificatePinner
  @Lorg/jetbrains/annotations/NotNull;() // invisible

  // access flags 0x2
  private Lokhttp3/internal/tls/CertificateChainCleaner; certificateChainCleaner
  @Lorg/jetbrains/annotations/Nullable;() // invisible

  // access flags 0x2
  private I callTimeout

  // access flags 0x2
  private I connectTimeout

  // access flags 0x2
  private I readTimeout

  // access flags 0x2
  private I writeTimeout

  // access flags 0x2
  private I pingInterval

  // access flags 0x2
  private J minWebSocketMessageToCompress

  // access flags 0x2
  private Lokhttp3/internal/connection/RouteDatabase; routeDatabase
  @Lorg/jetbrains/annotations/Nullable;() // invisible

  // access flags 0x1
  public <init>()V
   L0
    LINENUMBER 469 L0
    ALOAD 0
    INVOKESPECIAL java/lang/Object.<init> ()V
   L1
    LINENUMBER 470 L1
    ALOAD 0
    NEW okhttp3/Dispatcher
    DUP
    INVOKESPECIAL okhttp3/Dispatcher.<init> ()V
    PUTFIELD okhttp3/OkHttpClient$Builder.dispatcher : Lokhttp3/Dispatcher;
   L2
    LINENUMBER 471 L2
    ALOAD 0
    NEW okhttp3/ConnectionPool
    DUP
    INVOKESPECIAL okhttp3/ConnectionPool.<init> ()V
    PUTFIELD okhttp3/OkHttpClient$Builder.connectionPool : Lokhttp3/ConnectionPool;
   L3
    LINENUMBER 472 L3
    ALOAD 0
    NEW java/util/ArrayList
    DUP
    INVOKESPECIAL java/util/ArrayList.<init> ()V
    CHECKCAST java/util/List
   L4
    LINENUMBER 472 L4
    PUTFIELD okhttp3/OkHttpClient$Builder.interceptors : Ljava/util/List;
   L5
    LINENUMBER 473 L5
    ALOAD 0
    NEW java/util/ArrayList
    DUP
    INVOKESPECIAL java/util/ArrayList.<init> ()V
    CHECKCAST java/util/List
   L6
    LINENUMBER 473 L6
    PUTFIELD okhttp3/OkHttpClient$Builder.networkInterceptors : Ljava/util/List;
   L7
    LINENUMBER 474 L7
    ALOAD 0
    GETSTATIC okhttp3/EventListener.NONE : Lokhttp3/EventListener;
    INVOKESTATIC okhttp3/internal/Util.asFactory (Lokhttp3/EventListener;)Lokhttp3/EventListener$Factory;
    PUTFIELD okhttp3/OkHttpClient$Builder.eventListenerFactory : Lokhttp3/EventListener$Factory;
   L8
    LINENUMBER 475 L8
    ALOAD 0
    ICONST_1
    PUTFIELD okhttp3/OkHttpClient$Builder.retryOnConnectionFailure : Z
   L9
    LINENUMBER 476 L9
    ALOAD 0
    GETSTATIC okhttp3/Authenticator.NONE : Lokhttp3/Authenticator;
    PUTFIELD okhttp3/OkHttpClient$Builder.authenticator : Lokhttp3/Authenticator;
   L10
    LINENUMBER 477 L10
    ALOAD 0
    ICONST_1
    PUTFIELD okhttp3/OkHttpClient$Builder.followRedirects : Z
   L11
    LINENUMBER 478 L11
    ALOAD 0
    ICONST_1
    PUTFIELD okhttp3/OkHttpClient$Builder.followSslRedirects : Z
   L12
    LINENUMBER 479 L12
    ALOAD 0
    GETSTATIC okhttp3/CookieJar.NO_COOKIES : Lokhttp3/CookieJar;
    PUTFIELD okhttp3/OkHttpClient$Builder.cookieJar : Lokhttp3/CookieJar;
   L13
    LINENUMBER 481 L13
    ALOAD 0
    GETSTATIC okhttp3/Dns.SYSTEM : Lokhttp3/Dns;
    PUTFIELD okhttp3/OkHttpClient$Builder.dns : Lokhttp3/Dns;
   L14
    LINENUMBER 484 L14
    ALOAD 0
    GETSTATIC okhttp3/Authenticator.NONE : Lokhttp3/Authenticator;
    PUTFIELD okhttp3/OkHttpClient$Builder.proxyAuthenticator : Lokhttp3/Authenticator;
   L15
    LINENUMBER 485 L15
    ALOAD 0
    INVOKESTATIC javax/net/SocketFactory.getDefault ()Ljavax/net/SocketFactory;
    DUP
    LDC "getDefault()"
    INVOKESTATIC kotlin/jvm/internal/Intrinsics.checkNotNullExpressionValue (Ljava/lang/Object;Ljava/lang/String;)V
    PUTFIELD okhttp3/OkHttpClient$Builder.socketFactory : Ljavax/net/SocketFactory;
   L16
    LINENUMBER 488 L16
    ALOAD 0
    GETSTATIC okhttp3/OkHttpClient.Companion : Lokhttp3/OkHttpClient$Companion;
    INVOKEVIRTUAL okhttp3/OkHttpClient$Companion.getDEFAULT_CONNECTION_SPECS$okhttp ()Ljava/util/List;
    PUTFIELD okhttp3/OkHttpClient$Builder.connectionSpecs : Ljava/util/List;
   L17
    LINENUMBER 489 L17
    ALOAD 0
    GETSTATIC okhttp3/OkHttpClient.Companion : Lokhttp3/OkHttpClient$Companion;
    INVOKEVIRTUAL okhttp3/OkHttpClient$Companion.getDEFAULT_PROTOCOLS$okhttp ()Ljava/util/List;
    PUTFIELD okhttp3/OkHttpClient$Builder.protocols : Ljava/util/List;
   L18
    LINENUMBER 490 L18
    ALOAD 0
    GETSTATIC okhttp3/internal/tls/OkHostnameVerifier.INSTANCE : Lokhttp3/internal/tls/OkHostnameVerifier;
    CHECKCAST javax/net/ssl/HostnameVerifier
    PUTFIELD okhttp3/OkHttpClient$Builder.hostnameVerifier : Ljavax/net/ssl/HostnameVerifier;
   L19
    LINENUMBER 491 L19
    ALOAD 0
    GETSTATIC okhttp3/CertificatePinner.DEFAULT : Lokhttp3/CertificatePinner;
    PUTFIELD okhttp3/OkHttpClient$Builder.certificatePinner : Lokhttp3/CertificatePinner;
   L20
    LINENUMBER 494 L20
    ALOAD 0
    SIPUSH 10000
    PUTFIELD okhttp3/OkHttpClient$Builder.connectTimeout : I
   L21
    LINENUMBER 495 L21
    ALOAD 0
    SIPUSH 10000
    PUTFIELD okhttp3/OkHttpClient$Builder.readTimeout : I
   L22
    LINENUMBER 496 L22
    ALOAD 0
    SIPUSH 10000
    PUTFIELD okhttp3/OkHttpClient$Builder.writeTimeout : I
   L23
    LINENUMBER 498 L23
    ALOAD 0
    LDC 1024
    PUTFIELD okhttp3/OkHttpClient$Builder.minWebSocketMessageToCompress : J
   L24
    LINENUMBER 469 L24
    RETURN
   L25
    LOCALVARIABLE this Lokhttp3/OkHttpClient$Builder; L0 L25 0
    MAXSTACK = 4
    MAXLOCALS = 1

  // access flags 0x11
  public final getDispatcher$okhttp()Lokhttp3/Dispatcher;
  @Lorg/jetbrains/annotations/NotNull;() // invisible
   L0
    LINENUMBER 470 L0
    ALOAD 0
    GETFIELD okhttp3/OkHttpClient$Builder.dispatcher : Lokhttp3/Dispatcher;
    ARETURN
   L1
    LOCALVARIABLE this Lokhttp3/OkHttpClient$Builder; L0 L1 0
    MAXSTACK = 1
    MAXLOCALS = 1

  // access flags 0x11
  public final setDispatcher$okhttp(Lokhttp3/Dispatcher;)V
    // annotable parameter count: 1 (invisible)
    @Lorg/jetbrains/annotations/NotNull;() // invisible, parameter 0
   L0
    ALOAD 1
    LDC "<set-?>"
    INVOKESTATIC kotlin/jvm/internal/Intrinsics.checkNotNullParameter (Ljava/lang/Object;Ljava/lang/String;)V
   L1
    LINENUMBER 470 L1
    ALOAD 0
    ALOAD 1
    PUTFIELD okhttp3/OkHttpClient$Builder.dispatcher : Lokhttp3/Dispatcher;
    RETURN
   L2
    LOCALVARIABLE this Lokhttp3/OkHttpClient$Builder; L0 L2 0
    LOCALVARIABLE <set-?> Lokhttp3/Dispatcher; L0 L2 1
    MAXSTACK = 2
    MAXLOCALS = 2

  // access flags 0x11
  public final getConnectionPool$okhttp()Lokhttp3/ConnectionPool;
  @Lorg/jetbrains/annotations/NotNull;() // invisible
   L0
    LINENUMBER 471 L0
    ALOAD 0
    GETFIELD okhttp3/OkHttpClient$Builder.connectionPool : Lokhttp3/ConnectionPool;
    ARETURN
   L1
    LOCALVARIABLE this Lokhttp3/OkHttpClient$Builder; L0 L1 0
    MAXSTACK = 1
    MAXLOCALS = 1

  // access flags 0x11
  public final setConnectionPool$okhttp(Lokhttp3/ConnectionPool;)V
    // annotable parameter count: 1 (invisible)
    @Lorg/jetbrains/annotations/NotNull;() // invisible, parameter 0
   L0
    ALOAD 1
    LDC "<set-?>"
    INVOKESTATIC kotlin/jvm/internal/Intrinsics.checkNotNullParameter (Ljava/lang/Object;Ljava/lang/String;)V
   L1
    LINENUMBER 471 L1
    ALOAD 0
    ALOAD 1
    PUTFIELD okhttp3/OkHttpClient$Builder.connectionPool : Lokhttp3/ConnectionPool;
    RETURN
   L2
    LOCALVARIABLE this Lokhttp3/OkHttpClient$Builder; L0 L2 0
    LOCALVARIABLE <set-?> Lokhttp3/ConnectionPool; L0 L2 1
    MAXSTACK = 2
    MAXLOCALS = 2

  // access flags 0x11
  // signature ()Ljava/util/List<Lokhttp3/Interceptor;>;
  // declaration: java.util.List<okhttp3.Interceptor> getInterceptors$okhttp()
  public final getInterceptors$okhttp()Ljava/util/List;
  @Lorg/jetbrains/annotations/NotNull;() // invisible
   L0
    LINENUMBER 472 L0
    ALOAD 0
    GETFIELD okhttp3/OkHttpClient$Builder.interceptors : Ljava/util/List;
    ARETURN
   L1
    LOCALVARIABLE this Lokhttp3/OkHttpClient$Builder; L0 L1 0
    MAXSTACK = 1
    MAXLOCALS = 1

  // access flags 0x11
  // signature ()Ljava/util/List<Lokhttp3/Interceptor;>;
  // declaration: java.util.List<okhttp3.Interceptor> getNetworkInterceptors$okhttp()
  public final getNetworkInterceptors$okhttp()Ljava/util/List;
  @Lorg/jetbrains/annotations/NotNull;() // invisible
   L0
    LINENUMBER 473 L0
    ALOAD 0
    GETFIELD okhttp3/OkHttpClient$Builder.networkInterceptors : Ljava/util/List;
    ARETURN
   L1
    LOCALVARIABLE this Lokhttp3/OkHttpClient$Builder; L0 L1 0
    MAXSTACK = 1
    MAXLOCALS = 1

  // access flags 0x11
  public final getEventListenerFactory$okhttp()Lokhttp3/EventListener$Factory;
  @Lorg/jetbrains/annotations/NotNull;() // invisible
   L0
    LINENUMBER 474 L0
    ALOAD 0
    GETFIELD okhttp3/OkHttpClient$Builder.eventListenerFactory : Lokhttp3/EventListener$Factory;
    ARETURN
   L1
    LOCALVARIABLE this Lokhttp3/OkHttpClient$Builder; L0 L1 0
    MAXSTACK = 1
    MAXLOCALS = 1

  // access flags 0x11
  public final setEventListenerFactory$okhttp(Lokhttp3/EventListener$Factory;)V
    // annotable parameter count: 1 (invisible)
    @Lorg/jetbrains/annotations/NotNull;() // invisible, parameter 0
   L0
    ALOAD 1
    LDC "<set-?>"
    INVOKESTATIC kotlin/jvm/internal/Intrinsics.checkNotNullParameter (Ljava/lang/Object;Ljava/lang/String;)V
   L1
    LINENUMBER 474 L1
    ALOAD 0
    ALOAD 1
    PUTFIELD okhttp3/OkHttpClient$Builder.eventListenerFactory : Lokhttp3/EventListener$Factory;
    RETURN
   L2
    LOCALVARIABLE this Lokhttp3/OkHttpClient$Builder; L0 L2 0
    LOCALVARIABLE <set-?> Lokhttp3/EventListener$Factory; L0 L2 1
    MAXSTACK = 2
    MAXLOCALS = 2

  // access flags 0x11
  public final getRetryOnConnectionFailure$okhttp()Z
   L0
    LINENUMBER 475 L0
    ALOAD 0
    GETFIELD okhttp3/OkHttpClient$Builder.retryOnConnectionFailure : Z
    IRETURN
   L1
    LOCALVARIABLE this Lokhttp3/OkHttpClient$Builder; L0 L1 0
    MAXSTACK = 1
    MAXLOCALS = 1

  // access flags 0x11
  public final setRetryOnConnectionFailure$okhttp(Z)V
   L0
    LINENUMBER 475 L0
    ALOAD 0
    ILOAD 1
    PUTFIELD okhttp3/OkHttpClient$Builder.retryOnConnectionFailure : Z
    RETURN
   L1
    LOCALVARIABLE this Lokhttp3/OkHttpClient$Builder; L0 L1 0
    LOCALVARIABLE <set-?> Z L0 L1 1
    MAXSTACK = 2
    MAXLOCALS = 2

  // access flags 0x11
  public final getAuthenticator$okhttp()Lokhttp3/Authenticator;
  @Lorg/jetbrains/annotations/NotNull;() // invisible
   L0
    LINENUMBER 476 L0
    ALOAD 0
    GETFIELD okhttp3/OkHttpClient$Builder.authenticator : Lokhttp3/Authenticator;
    ARETURN
   L1
    LOCALVARIABLE this Lokhttp3/OkHttpClient$Builder; L0 L1 0
    MAXSTACK = 1
    MAXLOCALS = 1

  // access flags 0x11
  public final setAuthenticator$okhttp(Lokhttp3/Authenticator;)V
    // annotable parameter count: 1 (invisible)
    @Lorg/jetbrains/annotations/NotNull;() // invisible, parameter 0
   L0
    ALOAD 1
    LDC "<set-?>"
    INVOKESTATIC kotlin/jvm/internal/Intrinsics.checkNotNullParameter (Ljava/lang/Object;Ljava/lang/String;)V
   L1
    LINENUMBER 476 L1
    ALOAD 0
    ALOAD 1
    PUTFIELD okhttp3/OkHttpClient$Builder.authenticator : Lokhttp3/Authenticator;
    RETURN
   L2
    LOCALVARIABLE this Lokhttp3/OkHttpClient$Builder; L0 L2 0
    LOCALVARIABLE <set-?> Lokhttp3/Authenticator; L0 L2 1
    MAXSTACK = 2
    MAXLOCALS = 2

  // access flags 0x11
  public final getFollowRedirects$okhttp()Z
   L0
    LINENUMBER 477 L0
    ALOAD 0
    GETFIELD okhttp3/OkHttpClient$Builder.followRedirects : Z
    IRETURN
   L1
    LOCALVARIABLE this Lokhttp3/OkHttpClient$Builder; L0 L1 0
    MAXSTACK = 1
    MAXLOCALS = 1

  // access flags 0x11
  public final setFollowRedirects$okhttp(Z)V
   L0
    LINENUMBER 477 L0
    ALOAD 0
    ILOAD 1
    PUTFIELD okhttp3/OkHttpClient$Builder.followRedirects : Z
    RETURN
   L1
    LOCALVARIABLE this Lokhttp3/OkHttpClient$Builder; L0 L1 0
    LOCALVARIABLE <set-?> Z L0 L1 1
    MAXSTACK = 2
    MAXLOCALS = 2

  // access flags 0x11
  public final getFollowSslRedirects$okhttp()Z
   L0
    LINENUMBER 478 L0
    ALOAD 0
    GETFIELD okhttp3/OkHttpClient$Builder.followSslRedirects : Z
    IRETURN
   L1
    LOCALVARIABLE this Lokhttp3/OkHttpClient$Builder; L0 L1 0
    MAXSTACK = 1
    MAXLOCALS = 1

  // access flags 0x11
  public final setFollowSslRedirects$okhttp(Z)V
   L0
    LINENUMBER 478 L0
    ALOAD 0
    ILOAD 1
    PUTFIELD okhttp3/OkHttpClient$Builder.followSslRedirects : Z
    RETURN
   L1
    LOCALVARIABLE this Lokhttp3/OkHttpClient$Builder; L0 L1 0
    LOCALVARIABLE <set-?> Z L0 L1 1
    MAXSTACK = 2
    MAXLOCALS = 2

  // access flags 0x11
  public final getCookieJar$okhttp()Lokhttp3/CookieJar;
  @Lorg/jetbrains/annotations/NotNull;() // invisible
   L0
    LINENUMBER 479 L0
    ALOAD 0
    GETFIELD okhttp3/OkHttpClient$Builder.cookieJar : Lokhttp3/CookieJar;
    ARETURN
   L1
    LOCALVARIABLE this Lokhttp3/OkHttpClient$Builder; L0 L1 0
    MAXSTACK = 1
    MAXLOCALS = 1

  // access flags 0x11
  public final setCookieJar$okhttp(Lokhttp3/CookieJar;)V
    // annotable parameter count: 1 (invisible)
    @Lorg/jetbrains/annotations/NotNull;() // invisible, parameter 0
   L0
    ALOAD 1
    LDC "<set-?>"
    INVOKESTATIC kotlin/jvm/internal/Intrinsics.checkNotNullParameter (Ljava/lang/Object;Ljava/lang/String;)V
   L1
    LINENUMBER 479 L1
    ALOAD 0
    ALOAD 1
    PUTFIELD okhttp3/OkHttpClient$Builder.cookieJar : Lokhttp3/CookieJar;
    RETURN
   L2
    LOCALVARIABLE this Lokhttp3/OkHttpClient$Builder; L0 L2 0
    LOCALVARIABLE <set-?> Lokhttp3/CookieJar; L0 L2 1
    MAXSTACK = 2
    MAXLOCALS = 2

  // access flags 0x11
  public final getCache$okhttp()Lokhttp3/Cache;
  @Lorg/jetbrains/annotations/Nullable;() // invisible
   L0
    LINENUMBER 480 L0
    ALOAD 0
    GETFIELD okhttp3/OkHttpClient$Builder.cache : Lokhttp3/Cache;
    ARETURN
   L1
    LOCALVARIABLE this Lokhttp3/OkHttpClient$Builder; L0 L1 0
    MAXSTACK = 1
    MAXLOCALS = 1

  // access flags 0x11
  public final setCache$okhttp(Lokhttp3/Cache;)V
    // annotable parameter count: 1 (invisible)
    @Lorg/jetbrains/annotations/Nullable;() // invisible, parameter 0
   L0
    LINENUMBER 480 L0
    ALOAD 0
    ALOAD 1
    PUTFIELD okhttp3/OkHttpClient$Builder.cache : Lokhttp3/Cache;
    RETURN
   L1
    LOCALVARIABLE this Lokhttp3/OkHttpClient$Builder; L0 L1 0
    LOCALVARIABLE <set-?> Lokhttp3/Cache; L0 L1 1
    MAXSTACK = 2
    MAXLOCALS = 2

  // access flags 0x11
  public final getDns$okhttp()Lokhttp3/Dns;
  @Lorg/jetbrains/annotations/NotNull;() // invisible
   L0
    LINENUMBER 481 L0
    ALOAD 0
    GETFIELD okhttp3/OkHttpClient$Builder.dns : Lokhttp3/Dns;
    ARETURN
   L1
    LOCALVARIABLE this Lokhttp3/OkHttpClient$Builder; L0 L1 0
    MAXSTACK = 1
    MAXLOCALS = 1

  // access flags 0x11
  public final setDns$okhttp(Lokhttp3/Dns;)V
    // annotable parameter count: 1 (invisible)
    @Lorg/jetbrains/annotations/NotNull;() // invisible, parameter 0
   L0
    ALOAD 1
    LDC "<set-?>"
    INVOKESTATIC kotlin/jvm/internal/Intrinsics.checkNotNullParameter (Ljava/lang/Object;Ljava/lang/String;)V
   L1
    LINENUMBER 481 L1
    ALOAD 0
    ALOAD 1
    PUTFIELD okhttp3/OkHttpClient$Builder.dns : Lokhttp3/Dns;
    RETURN
   L2
    LOCALVARIABLE this Lokhttp3/OkHttpClient$Builder; L0 L2 0
    LOCALVARIABLE <set-?> Lokhttp3/Dns; L0 L2 1
    MAXSTACK = 2
    MAXLOCALS = 2

  // access flags 0x11
  public final getProxy$okhttp()Ljava/net/Proxy;
  @Lorg/jetbrains/annotations/Nullable;() // invisible
   L0
    LINENUMBER 482 L0
    ALOAD 0
    GETFIELD okhttp3/OkHttpClient$Builder.proxy : Ljava/net/Proxy;
    ARETURN
   L1
    LOCALVARIABLE this Lokhttp3/OkHttpClient$Builder; L0 L1 0
    MAXSTACK = 1
    MAXLOCALS = 1

  // access flags 0x11
  public final setProxy$okhttp(Ljava/net/Proxy;)V
    // annotable parameter count: 1 (invisible)
    @Lorg/jetbrains/annotations/Nullable;() // invisible, parameter 0
   L0
    LINENUMBER 482 L0
    ALOAD 0
    ALOAD 1
    PUTFIELD okhttp3/OkHttpClient$Builder.proxy : Ljava/net/Proxy;
    RETURN
   L1
    LOCALVARIABLE this Lokhttp3/OkHttpClient$Builder; L0 L1 0
    LOCALVARIABLE <set-?> Ljava/net/Proxy; L0 L1 1
    MAXSTACK = 2
    MAXLOCALS = 2

  // access flags 0x11
  public final getProxySelector$okhttp()Ljava/net/ProxySelector;
  @Lorg/jetbrains/annotations/Nullable;() // invisible
   L0
    LINENUMBER 483 L0
    ALOAD 0
    GETFIELD okhttp3/OkHttpClient$Builder.proxySelector : Ljava/net/ProxySelector;
    ARETURN
   L1
    LOCALVARIABLE this Lokhttp3/OkHttpClient$Builder; L0 L1 0
    MAXSTACK = 1
    MAXLOCALS = 1

  // access flags 0x11
  public final setProxySelector$okhttp(Ljava/net/ProxySelector;)V
    // annotable parameter count: 1 (invisible)
    @Lorg/jetbrains/annotations/Nullable;() // invisible, parameter 0
   L0
    LINENUMBER 483 L0
    ALOAD 0
    ALOAD 1
    PUTFIELD okhttp3/OkHttpClient$Builder.proxySelector : Ljava/net/ProxySelector;
    RETURN
   L1
    LOCALVARIABLE this Lokhttp3/OkHttpClient$Builder; L0 L1 0
    LOCALVARIABLE <set-?> Ljava/net/ProxySelector; L0 L1 1
    MAXSTACK = 2
    MAXLOCALS = 2

  // access flags 0x11
  public final getProxyAuthenticator$okhttp()Lokhttp3/Authenticator;
  @Lorg/jetbrains/annotations/NotNull;() // invisible
   L0
    LINENUMBER 484 L0
    ALOAD 0
    GETFIELD okhttp3/OkHttpClient$Builder.proxyAuthenticator : Lokhttp3/Authenticator;
    ARETURN
   L1
    LOCALVARIABLE this Lokhttp3/OkHttpClient$Builder; L0 L1 0
    MAXSTACK = 1
    MAXLOCALS = 1

  // access flags 0x11
  public final setProxyAuthenticator$okhttp(Lokhttp3/Authenticator;)V
    // annotable parameter count: 1 (invisible)
    @Lorg/jetbrains/annotations/NotNull;() // invisible, parameter 0
   L0
    ALOAD 1
    LDC "<set-?>"
    INVOKESTATIC kotlin/jvm/internal/Intrinsics.checkNotNullParameter (Ljava/lang/Object;Ljava/lang/String;)V
   L1
    LINENUMBER 484 L1
    ALOAD 0
    ALOAD 1
    PUTFIELD okhttp3/OkHttpClient$Builder.proxyAuthenticator : Lokhttp3/Authenticator;
    RETURN
   L2
    LOCALVARIABLE this Lokhttp3/OkHttpClient$Builder; L0 L2 0
    LOCALVARIABLE <set-?> Lokhttp3/Authenticator; L0 L2 1
    MAXSTACK = 2
    MAXLOCALS = 2

  // access flags 0x11
  public final getSocketFactory$okhttp()Ljavax/net/SocketFactory;
  @Lorg/jetbrains/annotations/NotNull;() // invisible
   L0
    LINENUMBER 485 L0
    ALOAD 0
    GETFIELD okhttp3/OkHttpClient$Builder.socketFactory : Ljavax/net/SocketFactory;
    ARETURN
   L1
    LOCALVARIABLE this Lokhttp3/OkHttpClient$Builder; L0 L1 0
    MAXSTACK = 1
    MAXLOCALS = 1

  // access flags 0x11
  public final setSocketFactory$okhttp(Ljavax/net/SocketFactory;)V
    // annotable parameter count: 1 (invisible)
    @Lorg/jetbrains/annotations/NotNull;() // invisible, parameter 0
   L0
    ALOAD 1
    LDC "<set-?>"
    INVOKESTATIC kotlin/jvm/internal/Intrinsics.checkNotNullParameter (Ljava/lang/Object;Ljava/lang/String;)V
   L1
    LINENUMBER 485 L1
    ALOAD 0
    ALOAD 1
    PUTFIELD okhttp3/OkHttpClient$Builder.socketFactory : Ljavax/net/SocketFactory;
    RETURN
   L2
    LOCALVARIABLE this Lokhttp3/OkHttpClient$Builder; L0 L2 0
    LOCALVARIABLE <set-?> Ljavax/net/SocketFactory; L0 L2 1
    MAXSTACK = 2
    MAXLOCALS = 2

  // access flags 0x11
  public final getSslSocketFactoryOrNull$okhttp()Ljavax/net/ssl/SSLSocketFactory;
  @Lorg/jetbrains/annotations/Nullable;() // invisible
   L0
    LINENUMBER 486 L0
    ALOAD 0
    GETFIELD okhttp3/OkHttpClient$Builder.sslSocketFactoryOrNull : Ljavax/net/ssl/SSLSocketFactory;
    ARETURN
   L1
    LOCALVARIABLE this Lokhttp3/OkHttpClient$Builder; L0 L1 0
    MAXSTACK = 1
    MAXLOCALS = 1

  // access flags 0x11
  public final setSslSocketFactoryOrNull$okhttp(Ljavax/net/ssl/SSLSocketFactory;)V
    // annotable parameter count: 1 (invisible)
    @Lorg/jetbrains/annotations/Nullable;() // invisible, parameter 0
   L0
    LINENUMBER 486 L0
    ALOAD 0
    ALOAD 1
    PUTFIELD okhttp3/OkHttpClient$Builder.sslSocketFactoryOrNull : Ljavax/net/ssl/SSLSocketFactory;
    RETURN
   L1
    LOCALVARIABLE this Lokhttp3/OkHttpClient$Builder; L0 L1 0
    LOCALVARIABLE <set-?> Ljavax/net/ssl/SSLSocketFactory; L0 L1 1
    MAXSTACK = 2
    MAXLOCALS = 2

  // access flags 0x11
  public final getX509TrustManagerOrNull$okhttp()Ljavax/net/ssl/X509TrustManager;
  @Lorg/jetbrains/annotations/Nullable;() // invisible
   L0
    LINENUMBER 487 L0
    ALOAD 0
    GETFIELD okhttp3/OkHttpClient$Builder.x509TrustManagerOrNull : Ljavax/net/ssl/X509TrustManager;
    ARETURN
   L1
    LOCALVARIABLE this Lokhttp3/OkHttpClient$Builder; L0 L1 0
    MAXSTACK = 1
    MAXLOCALS = 1

  // access flags 0x11
  public final setX509TrustManagerOrNull$okhttp(Ljavax/net/ssl/X509TrustManager;)V
    // annotable parameter count: 1 (invisible)
    @Lorg/jetbrains/annotations/Nullable;() // invisible, parameter 0
   L0
    LINENUMBER 487 L0
    ALOAD 0
    ALOAD 1
    PUTFIELD okhttp3/OkHttpClient$Builder.x509TrustManagerOrNull : Ljavax/net/ssl/X509TrustManager;
    RETURN
   L1
    LOCALVARIABLE this Lokhttp3/OkHttpClient$Builder; L0 L1 0
    LOCALVARIABLE <set-?> Ljavax/net/ssl/X509TrustManager; L0 L1 1
    MAXSTACK = 2
    MAXLOCALS = 2

  // access flags 0x11
  // signature ()Ljava/util/List<Lokhttp3/ConnectionSpec;>;
  // declaration: java.util.List<okhttp3.ConnectionSpec> getConnectionSpecs$okhttp()
  public final getConnectionSpecs$okhttp()Ljava/util/List;
  @Lorg/jetbrains/annotations/NotNull;() // invisible
   L0
    LINENUMBER 488 L0
    ALOAD 0
    GETFIELD okhttp3/OkHttpClient$Builder.connectionSpecs : Ljava/util/List;
    ARETURN
   L1
    LOCALVARIABLE this Lokhttp3/OkHttpClient$Builder; L0 L1 0
    MAXSTACK = 1
    MAXLOCALS = 1

  // access flags 0x11
  // signature (Ljava/util/List<Lokhttp3/ConnectionSpec;>;)V
  // declaration: void setConnectionSpecs$okhttp(java.util.List<okhttp3.ConnectionSpec>)
  public final setConnectionSpecs$okhttp(Ljava/util/List;)V
    // annotable parameter count: 1 (invisible)
    @Lorg/jetbrains/annotations/NotNull;() // invisible, parameter 0
   L0
    ALOAD 1
    LDC "<set-?>"
    INVOKESTATIC kotlin/jvm/internal/Intrinsics.checkNotNullParameter (Ljava/lang/Object;Ljava/lang/String;)V
   L1
    LINENUMBER 488 L1
    ALOAD 0
    ALOAD 1
    PUTFIELD okhttp3/OkHttpClient$Builder.connectionSpecs : Ljava/util/List;
    RETURN
   L2
    LOCALVARIABLE this Lokhttp3/OkHttpClient$Builder; L0 L2 0
    LOCALVARIABLE <set-?> Ljava/util/List; L0 L2 1
    MAXSTACK = 2
    MAXLOCALS = 2

  // access flags 0x11
  // signature ()Ljava/util/List<Lokhttp3/Protocol;>;
  // declaration: java.util.List<okhttp3.Protocol> getProtocols$okhttp()
  public final getProtocols$okhttp()Ljava/util/List;
  @Lorg/jetbrains/annotations/NotNull;() // invisible
   L0
    LINENUMBER 489 L0
    ALOAD 0
    GETFIELD okhttp3/OkHttpClient$Builder.protocols : Ljava/util/List;
    ARETURN
   L1
    LOCALVARIABLE this Lokhttp3/OkHttpClient$Builder; L0 L1 0
    MAXSTACK = 1
    MAXLOCALS = 1

  // access flags 0x11
  // signature (Ljava/util/List<+Lokhttp3/Protocol;>;)V
  // declaration: void setProtocols$okhttp(java.util.List<? extends okhttp3.Protocol>)
  public final setProtocols$okhttp(Ljava/util/List;)V
    // annotable parameter count: 1 (invisible)
    @Lorg/jetbrains/annotations/NotNull;() // invisible, parameter 0
   L0
    ALOAD 1
    LDC "<set-?>"
    INVOKESTATIC kotlin/jvm/internal/Intrinsics.checkNotNullParameter (Ljava/lang/Object;Ljava/lang/String;)V
   L1
    LINENUMBER 489 L1
    ALOAD 0
    ALOAD 1
    PUTFIELD okhttp3/OkHttpClient$Builder.protocols : Ljava/util/List;
    RETURN
   L2
    LOCALVARIABLE this Lokhttp3/OkHttpClient$Builder; L0 L2 0
    LOCALVARIABLE <set-?> Ljava/util/List; L0 L2 1
    MAXSTACK = 2
    MAXLOCALS = 2

  // access flags 0x11
  public final getHostnameVerifier$okhttp()Ljavax/net/ssl/HostnameVerifier;
  @Lorg/jetbrains/annotations/NotNull;() // invisible
   L0
    LINENUMBER 490 L0
    ALOAD 0
    GETFIELD okhttp3/OkHttpClient$Builder.hostnameVerifier : Ljavax/net/ssl/HostnameVerifier;
    ARETURN
   L1
    LOCALVARIABLE this Lokhttp3/OkHttpClient$Builder; L0 L1 0
    MAXSTACK = 1
    MAXLOCALS = 1

  // access flags 0x11
  public final setHostnameVerifier$okhttp(Ljavax/net/ssl/HostnameVerifier;)V
    // annotable parameter count: 1 (invisible)
    @Lorg/jetbrains/annotations/NotNull;() // invisible, parameter 0
   L0
    ALOAD 1
    LDC "<set-?>"
    INVOKESTATIC kotlin/jvm/internal/Intrinsics.checkNotNullParameter (Ljava/lang/Object;Ljava/lang/String;)V
   L1
    LINENUMBER 490 L1
    ALOAD 0
    ALOAD 1
    PUTFIELD okhttp3/OkHttpClient$Builder.hostnameVerifier : Ljavax/net/ssl/HostnameVerifier;
    RETURN
   L2
    LOCALVARIABLE this Lokhttp3/OkHttpClient$Builder; L0 L2 0
    LOCALVARIABLE <set-?> Ljavax/net/ssl/HostnameVerifier; L0 L2 1
    MAXSTACK = 2
    MAXLOCALS = 2

  // access flags 0x11
  public final getCertificatePinner$okhttp()Lokhttp3/CertificatePinner;
  @Lorg/jetbrains/annotations/NotNull;() // invisible
   L0
    LINENUMBER 491 L0
    ALOAD 0
    GETFIELD okhttp3/OkHttpClient$Builder.certificatePinner : Lokhttp3/CertificatePinner;
    ARETURN
   L1
    LOCALVARIABLE this Lokhttp3/OkHttpClient$Builder; L0 L1 0
    MAXSTACK = 1
    MAXLOCALS = 1

  // access flags 0x11
  public final setCertificatePinner$okhttp(Lokhttp3/CertificatePinner;)V
    // annotable parameter count: 1 (invisible)
    @Lorg/jetbrains/annotations/NotNull;() // invisible, parameter 0
   L0
    ALOAD 1
    LDC "<set-?>"
    INVOKESTATIC kotlin/jvm/internal/Intrinsics.checkNotNullParameter (Ljava/lang/Object;Ljava/lang/String;)V
   L1
    LINENUMBER 491 L1
    ALOAD 0
    ALOAD 1
    PUTFIELD okhttp3/OkHttpClient$Builder.certificatePinner : Lokhttp3/CertificatePinner;
    RETURN
   L2
    LOCALVARIABLE this Lokhttp3/OkHttpClient$Builder; L0 L2 0
    LOCALVARIABLE <set-?> Lokhttp3/CertificatePinner; L0 L2 1
    MAXSTACK = 2
    MAXLOCALS = 2

  // access flags 0x11
  public final getCertificateChainCleaner$okhttp()Lokhttp3/internal/tls/CertificateChainCleaner;
  @Lorg/jetbrains/annotations/Nullable;() // invisible
   L0
    LINENUMBER 492 L0
    ALOAD 0
    GETFIELD okhttp3/OkHttpClient$Builder.certificateChainCleaner : Lokhttp3/internal/tls/CertificateChainCleaner;
    ARETURN
   L1
    LOCALVARIABLE this Lokhttp3/OkHttpClient$Builder; L0 L1 0
    MAXSTACK = 1
    MAXLOCALS = 1

  // access flags 0x11
  public final setCertificateChainCleaner$okhttp(Lokhttp3/internal/tls/CertificateChainCleaner;)V
    // annotable parameter count: 1 (invisible)
    @Lorg/jetbrains/annotations/Nullable;() // invisible, parameter 0
   L0
    LINENUMBER 492 L0
    ALOAD 0
    ALOAD 1
    PUTFIELD okhttp3/OkHttpClient$Builder.certificateChainCleaner : Lokhttp3/internal/tls/CertificateChainCleaner;
    RETURN
   L1
    LOCALVARIABLE this Lokhttp3/OkHttpClient$Builder; L0 L1 0
    LOCALVARIABLE <set-?> Lokhttp3/internal/tls/CertificateChainCleaner; L0 L1 1
    MAXSTACK = 2
    MAXLOCALS = 2

  // access flags 0x11
  public final getCallTimeout$okhttp()I
   L0
    LINENUMBER 493 L0
    ALOAD 0
    GETFIELD okhttp3/OkHttpClient$Builder.callTimeout : I
    IRETURN
   L1
    LOCALVARIABLE this Lokhttp3/OkHttpClient$Builder; L0 L1 0
    MAXSTACK = 1
    MAXLOCALS = 1

  // access flags 0x11
  public final setCallTimeout$okhttp(I)V
   L0
    LINENUMBER 493 L0
    ALOAD 0
    ILOAD 1
    PUTFIELD okhttp3/OkHttpClient$Builder.callTimeout : I
    RETURN
   L1
    LOCALVARIABLE this Lokhttp3/OkHttpClient$Builder; L0 L1 0
    LOCALVARIABLE <set-?> I L0 L1 1
    MAXSTACK = 2
    MAXLOCALS = 2

  // access flags 0x11
  public final getConnectTimeout$okhttp()I
   L0
    LINENUMBER 494 L0
    ALOAD 0
    GETFIELD okhttp3/OkHttpClient$Builder.connectTimeout : I
    IRETURN
   L1
    LOCALVARIABLE this Lokhttp3/OkHttpClient$Builder; L0 L1 0
    MAXSTACK = 1
    MAXLOCALS = 1

  // access flags 0x11
  public final setConnectTimeout$okhttp(I)V
   L0
    LINENUMBER 494 L0
    ALOAD 0
    ILOAD 1
    PUTFIELD okhttp3/OkHttpClient$Builder.connectTimeout : I
    RETURN
   L1
    LOCALVARIABLE this Lokhttp3/OkHttpClient$Builder; L0 L1 0
    LOCALVARIABLE <set-?> I L0 L1 1
    MAXSTACK = 2
    MAXLOCALS = 2

  // access flags 0x11
  public final getReadTimeout$okhttp()I
   L0
    LINENUMBER 495 L0
    ALOAD 0
    GETFIELD okhttp3/OkHttpClient$Builder.readTimeout : I
    IRETURN
   L1
    LOCALVARIABLE this Lokhttp3/OkHttpClient$Builder; L0 L1 0
    MAXSTACK = 1
    MAXLOCALS = 1

  // access flags 0x11
  public final setReadTimeout$okhttp(I)V
   L0
    LINENUMBER 495 L0
    ALOAD 0
    ILOAD 1
    PUTFIELD okhttp3/OkHttpClient$Builder.readTimeout : I
    RETURN
   L1
    LOCALVARIABLE this Lokhttp3/OkHttpClient$Builder; L0 L1 0
    LOCALVARIABLE <set-?> I L0 L1 1
    MAXSTACK = 2
    MAXLOCALS = 2

  // access flags 0x11
  public final getWriteTimeout$okhttp()I
   L0
    LINENUMBER 496 L0
    ALOAD 0
    GETFIELD okhttp3/OkHttpClient$Builder.writeTimeout : I
    IRETURN
   L1
    LOCALVARIABLE this Lokhttp3/OkHttpClient$Builder; L0 L1 0
    MAXSTACK = 1
    MAXLOCALS = 1

  // access flags 0x11
  public final setWriteTimeout$okhttp(I)V
   L0
    LINENUMBER 496 L0
    ALOAD 0
    ILOAD 1
    PUTFIELD okhttp3/OkHttpClient$Builder.writeTimeout : I
    RETURN
   L1
    LOCALVARIABLE this Lokhttp3/OkHttpClient$Builder; L0 L1 0
    LOCALVARIABLE <set-?> I L0 L1 1
    MAXSTACK = 2
    MAXLOCALS = 2

  // access flags 0x11
  public final getPingInterval$okhttp()I
   L0
    LINENUMBER 497 L0
    ALOAD 0
    GETFIELD okhttp3/OkHttpClient$Builder.pingInterval : I
    IRETURN
   L1
    LOCALVARIABLE this Lokhttp3/OkHttpClient$Builder; L0 L1 0
    MAXSTACK = 1
    MAXLOCALS = 1

  // access flags 0x11
  public final setPingInterval$okhttp(I)V
   L0
    LINENUMBER 497 L0
    ALOAD 0
    ILOAD 1
    PUTFIELD okhttp3/OkHttpClient$Builder.pingInterval : I
    RETURN
   L1
    LOCALVARIABLE this Lokhttp3/OkHttpClient$Builder; L0 L1 0
    LOCALVARIABLE <set-?> I L0 L1 1
    MAXSTACK = 2
    MAXLOCALS = 2

  // access flags 0x11
  public final getMinWebSocketMessageToCompress$okhttp()J
   L0
    LINENUMBER 498 L0
    ALOAD 0
    GETFIELD okhttp3/OkHttpClient$Builder.minWebSocketMessageToCompress : J
    LRETURN
   L1
    LOCALVARIABLE this Lokhttp3/OkHttpClient$Builder; L0 L1 0
    MAXSTACK = 2
    MAXLOCALS = 1

  // access flags 0x11
  public final setMinWebSocketMessageToCompress$okhttp(J)V
   L0
    LINENUMBER 498 L0
    ALOAD 0
    LLOAD 1
    PUTFIELD okhttp3/OkHttpClient$Builder.minWebSocketMessageToCompress : J
    RETURN
   L1
    LOCALVARIABLE this Lokhttp3/OkHttpClient$Builder; L0 L1 0
    LOCALVARIABLE <set-?> J L0 L1 1
    MAXSTACK = 3
    MAXLOCALS = 3

  // access flags 0x11
  public final getRouteDatabase$okhttp()Lokhttp3/internal/connection/RouteDatabase;
  @Lorg/jetbrains/annotations/Nullable;() // invisible
   L0
    LINENUMBER 499 L0
    ALOAD 0
    GETFIELD okhttp3/OkHttpClient$Builder.routeDatabase : Lokhttp3/internal/connection/RouteDatabase;
    ARETURN
   L1
    LOCALVARIABLE this Lokhttp3/OkHttpClient$Builder; L0 L1 0
    MAXSTACK = 1
    MAXLOCALS = 1

  // access flags 0x11
  public final setRouteDatabase$okhttp(Lokhttp3/internal/connection/RouteDatabase;)V
    // annotable parameter count: 1 (invisible)
    @Lorg/jetbrains/annotations/Nullable;() // invisible, parameter 0
   L0
    LINENUMBER 499 L0
    ALOAD 0
    ALOAD 1
    PUTFIELD okhttp3/OkHttpClient$Builder.routeDatabase : Lokhttp3/internal/connection/RouteDatabase;
    RETURN
   L1
    LOCALVARIABLE this Lokhttp3/OkHttpClient$Builder; L0 L1 0
    LOCALVARIABLE <set-?> Lokhttp3/internal/connection/RouteDatabase; L0 L1 1
    MAXSTACK = 2
    MAXLOCALS = 2

  // access flags 0x1
  public <init>(Lokhttp3/OkHttpClient;)V
    // annotable parameter count: 1 (invisible)
    @Lorg/jetbrains/annotations/NotNull;() // invisible, parameter 0
   L0
    ALOAD 1
    LDC "okHttpClient"
    INVOKESTATIC kotlin/jvm/internal/Intrinsics.checkNotNullParameter (Ljava/lang/Object;Ljava/lang/String;)V
   L1
    LINENUMBER 501 L1
    ALOAD 0
    INVOKESPECIAL okhttp3/OkHttpClient$Builder.<init> ()V
   L2
    LINENUMBER 502 L2
    ALOAD 0
    ALOAD 1
    INVOKEVIRTUAL okhttp3/OkHttpClient.dispatcher ()Lokhttp3/Dispatcher;
    PUTFIELD okhttp3/OkHttpClient$Builder.dispatcher : Lokhttp3/Dispatcher;
   L3
    LINENUMBER 503 L3
    ALOAD 0
    ALOAD 1
    INVOKEVIRTUAL okhttp3/OkHttpClient.connectionPool ()Lokhttp3/ConnectionPool;
    PUTFIELD okhttp3/OkHttpClient$Builder.connectionPool : Lokhttp3/ConnectionPool;
   L4
    LINENUMBER 504 L4
    ALOAD 0
    GETFIELD okhttp3/OkHttpClient$Builder.interceptors : Ljava/util/List;
    CHECKCAST java/util/Collection
    ALOAD 1
    INVOKEVIRTUAL okhttp3/OkHttpClient.interceptors ()Ljava/util/List;
    CHECKCAST java/lang/Iterable
    INVOKESTATIC kotlin/collections/CollectionsKt.addAll (Ljava/util/Collection;Ljava/lang/Iterable;)Z
    POP
   L5
    LINENUMBER 505 L5
    ALOAD 0
    GETFIELD okhttp3/OkHttpClient$Builder.networkInterceptors : Ljava/util/List;
    CHECKCAST java/util/Collection
    ALOAD 1
    INVOKEVIRTUAL okhttp3/OkHttpClient.networkInterceptors ()Ljava/util/List;
    CHECKCAST java/lang/Iterable
    INVOKESTATIC kotlin/collections/CollectionsKt.addAll (Ljava/util/Collection;Ljava/lang/Iterable;)Z
    POP
   L6
    LINENUMBER 506 L6
    ALOAD 0
    ALOAD 1
    INVOKEVIRTUAL okhttp3/OkHttpClient.eventListenerFactory ()Lokhttp3/EventListener$Factory;
    PUTFIELD okhttp3/OkHttpClient$Builder.eventListenerFactory : Lokhttp3/EventListener$Factory;
   L7
    LINENUMBER 507 L7
    ALOAD 0
    ALOAD 1
    INVOKEVIRTUAL okhttp3/OkHttpClient.retryOnConnectionFailure ()Z
    PUTFIELD okhttp3/OkHttpClient$Builder.retryOnConnectionFailure : Z
   L8
    LINENUMBER 508 L8
    ALOAD 0
    ALOAD 1
    INVOKEVIRTUAL okhttp3/OkHttpClient.authenticator ()Lokhttp3/Authenticator;
    PUTFIELD okhttp3/OkHttpClient$Builder.authenticator : Lokhttp3/Authenticator;
   L9
    LINENUMBER 509 L9
    ALOAD 0
    ALOAD 1
    INVOKEVIRTUAL okhttp3/OkHttpClient.followRedirects ()Z
    PUTFIELD okhttp3/OkHttpClient$Builder.followRedirects : Z
   L10
    LINENUMBER 510 L10
    ALOAD 0
    ALOAD 1
    INVOKEVIRTUAL okhttp3/OkHttpClient.followSslRedirects ()Z
    PUTFIELD okhttp3/OkHttpClient$Builder.followSslRedirects : Z
   L11
    LINENUMBER 511 L11
    ALOAD 0
    ALOAD 1
    INVOKEVIRTUAL okhttp3/OkHttpClient.cookieJar ()Lokhttp3/CookieJar;
    PUTFIELD okhttp3/OkHttpClient$Builder.cookieJar : Lokhttp3/CookieJar;
   L12
    LINENUMBER 512 L12
    ALOAD 0
    ALOAD 1
    INVOKEVIRTUAL okhttp3/OkHttpClient.cache ()Lokhttp3/Cache;
    PUTFIELD okhttp3/OkHttpClient$Builder.cache : Lokhttp3/Cache;
   L13
    LINENUMBER 513 L13
    ALOAD 0
    ALOAD 1
    INVOKEVIRTUAL okhttp3/OkHttpClient.dns ()Lokhttp3/Dns;
    PUTFIELD okhttp3/OkHttpClient$Builder.dns : Lokhttp3/Dns;
   L14
    LINENUMBER 514 L14
    ALOAD 0
    ALOAD 1
    INVOKEVIRTUAL okhttp3/OkHttpClient.proxy ()Ljava/net/Proxy;
    PUTFIELD okhttp3/OkHttpClient$Builder.proxy : Ljava/net/Proxy;
   L15
    LINENUMBER 515 L15
    ALOAD 0
    ALOAD 1
    INVOKEVIRTUAL okhttp3/OkHttpClient.proxySelector ()Ljava/net/ProxySelector;
    PUTFIELD okhttp3/OkHttpClient$Builder.proxySelector : Ljava/net/ProxySelector;
   L16
    LINENUMBER 516 L16
    ALOAD 0
    ALOAD 1
    INVOKEVIRTUAL okhttp3/OkHttpClient.proxyAuthenticator ()Lokhttp3/Authenticator;
    PUTFIELD okhttp3/OkHttpClient$Builder.proxyAuthenticator : Lokhttp3/Authenticator;
   L17
    LINENUMBER 517 L17
    ALOAD 0
    ALOAD 1
    INVOKEVIRTUAL okhttp3/OkHttpClient.socketFactory ()Ljavax/net/SocketFactory;
    PUTFIELD okhttp3/OkHttpClient$Builder.socketFactory : Ljavax/net/SocketFactory;
   L18
    LINENUMBER 518 L18
    ALOAD 0
    ALOAD 1
    INVOKESTATIC okhttp3/OkHttpClient.access$getSslSocketFactoryOrNull$p (Lokhttp3/OkHttpClient;)Ljavax/net/ssl/SSLSocketFactory;
    PUTFIELD okhttp3/OkHttpClient$Builder.sslSocketFactoryOrNull : Ljavax/net/ssl/SSLSocketFactory;
   L19
    LINENUMBER 519 L19
    ALOAD 0
    ALOAD 1
    INVOKEVIRTUAL okhttp3/OkHttpClient.x509TrustManager ()Ljavax/net/ssl/X509TrustManager;
    PUTFIELD okhttp3/OkHttpClient$Builder.x509TrustManagerOrNull : Ljavax/net/ssl/X509TrustManager;
   L20
    LINENUMBER 520 L20
    ALOAD 0
    ALOAD 1
    INVOKEVIRTUAL okhttp3/OkHttpClient.connectionSpecs ()Ljava/util/List;
    PUTFIELD okhttp3/OkHttpClient$Builder.connectionSpecs : Ljava/util/List;
   L21
    LINENUMBER 521 L21
    ALOAD 0
    ALOAD 1
    INVOKEVIRTUAL okhttp3/OkHttpClient.protocols ()Ljava/util/List;
    PUTFIELD okhttp3/OkHttpClient$Builder.protocols : Ljava/util/List;
   L22
    LINENUMBER 522 L22
    ALOAD 0
    ALOAD 1
    INVOKEVIRTUAL okhttp3/OkHttpClient.hostnameVerifier ()Ljavax/net/ssl/HostnameVerifier;
    PUTFIELD okhttp3/OkHttpClient$Builder.hostnameVerifier : Ljavax/net/ssl/HostnameVerifier;
   L23
    LINENUMBER 523 L23
    ALOAD 0
    ALOAD 1
    INVOKEVIRTUAL okhttp3/OkHttpClient.certificatePinner ()Lokhttp3/CertificatePinner;
    PUTFIELD okhttp3/OkHttpClient$Builder.certificatePinner : Lokhttp3/CertificatePinner;
   L24
    LINENUMBER 524 L24
    ALOAD 0
    ALOAD 1
    INVOKEVIRTUAL okhttp3/OkHttpClient.certificateChainCleaner ()Lokhttp3/internal/tls/CertificateChainCleaner;
    PUTFIELD okhttp3/OkHttpClient$Builder.certificateChainCleaner : Lokhttp3/internal/tls/CertificateChainCleaner;
   L25
    LINENUMBER 525 L25
    ALOAD 0
    ALOAD 1
    INVOKEVIRTUAL okhttp3/OkHttpClient.callTimeoutMillis ()I
    PUTFIELD okhttp3/OkHttpClient$Builder.callTimeout : I
   L26
    LINENUMBER 526 L26
    ALOAD 0
    ALOAD 1
    INVOKEVIRTUAL okhttp3/OkHttpClient.connectTimeoutMillis ()I
    PUTFIELD okhttp3/OkHttpClient$Builder.connectTimeout : I
   L27
    LINENUMBER 527 L27
    ALOAD 0
    ALOAD 1
    INVOKEVIRTUAL okhttp3/OkHttpClient.readTimeoutMillis ()I
    PUTFIELD okhttp3/OkHttpClient$Builder.readTimeout : I
   L28
    LINENUMBER 528 L28
    ALOAD 0
    ALOAD 1
    INVOKEVIRTUAL okhttp3/OkHttpClient.writeTimeoutMillis ()I
    PUTFIELD okhttp3/OkHttpClient$Builder.writeTimeout : I
   L29
    LINENUMBER 529 L29
    ALOAD 0
    ALOAD 1
    INVOKEVIRTUAL okhttp3/OkHttpClient.pingIntervalMillis ()I
    PUTFIELD okhttp3/OkHttpClient$Builder.pingInterval : I
   L30
    LINENUMBER 530 L30
    ALOAD 0
    ALOAD 1
    INVOKEVIRTUAL okhttp3/OkHttpClient.minWebSocketMessageToCompress ()J
    PUTFIELD okhttp3/OkHttpClient$Builder.minWebSocketMessageToCompress : J
   L31
    LINENUMBER 531 L31
    ALOAD 0
    ALOAD 1
    INVOKEVIRTUAL okhttp3/OkHttpClient.getRouteDatabase ()Lokhttp3/internal/connection/RouteDatabase;
    PUTFIELD okhttp3/OkHttpClient$Builder.routeDatabase : Lokhttp3/internal/connection/RouteDatabase;
   L32
    LINENUMBER 532 L32
    RETURN
   L33
    LOCALVARIABLE this Lokhttp3/OkHttpClient$Builder; L0 L33 0
    LOCALVARIABLE okHttpClient Lokhttp3/OkHttpClient; L0 L33 1
    MAXSTACK = 3
    MAXLOCALS = 2

  // access flags 0x11
  public final dispatcher(Lokhttp3/Dispatcher;)Lokhttp3/OkHttpClient$Builder;
  @Lorg/jetbrains/annotations/NotNull;() // invisible
    // annotable parameter count: 1 (invisible)
    @Lorg/jetbrains/annotations/NotNull;() // invisible, parameter 0
   L0
    ALOAD 1
    LDC "dispatcher"
    INVOKESTATIC kotlin/jvm/internal/Intrinsics.checkNotNullParameter (Ljava/lang/Object;Ljava/lang/String;)V
   L1
    LINENUMBER 537 L1
    ALOAD 0
    ASTORE 2
    ALOAD 2
    CHECKCAST okhttp3/OkHttpClient$Builder
    ASTORE 3
   L2
    ICONST_0
    ISTORE 4
   L3
    LINENUMBER 538 L3
    ALOAD 3
    ALOAD 1
    PUTFIELD okhttp3/OkHttpClient$Builder.dispatcher : Lokhttp3/Dispatcher;
   L4
    LINENUMBER 539 L4
    NOP
   L5
    LINENUMBER 537 L5
    ALOAD 2
    CHECKCAST okhttp3/OkHttpClient$Builder
   L6
    LINENUMBER 539 L6
    ARETURN
   L7
    LOCALVARIABLE $i$a$-apply-OkHttpClient$Builder$dispatcher$1 I L3 L5 4
    LOCALVARIABLE $this$dispatcher_u24lambda_u240 Lokhttp3/OkHttpClient$Builder; L2 L5 3
    LOCALVARIABLE this Lokhttp3/OkHttpClient$Builder; L0 L7 0
    LOCALVARIABLE dispatcher Lokhttp3/Dispatcher; L0 L7 1
    MAXSTACK = 2
    MAXLOCALS = 5

  // access flags 0x11
  public final connectionPool(Lokhttp3/ConnectionPool;)Lokhttp3/OkHttpClient$Builder;
  @Lorg/jetbrains/annotations/NotNull;() // invisible
    // annotable parameter count: 1 (invisible)
    @Lorg/jetbrains/annotations/NotNull;() // invisible, parameter 0
   L0
    ALOAD 1
    LDC "connectionPool"
    INVOKESTATIC kotlin/jvm/internal/Intrinsics.checkNotNullParameter (Ljava/lang/Object;Ljava/lang/String;)V
   L1
    LINENUMBER 546 L1
    ALOAD 0
    ASTORE 2
    ALOAD 2
    CHECKCAST okhttp3/OkHttpClient$Builder
    ASTORE 3
   L2
    ICONST_0
    ISTORE 4
   L3
    LINENUMBER 547 L3
    ALOAD 3
    ALOAD 1
    PUTFIELD okhttp3/OkHttpClient$Builder.connectionPool : Lokhttp3/ConnectionPool;
   L4
    LINENUMBER 548 L4
    NOP
   L5
    LINENUMBER 546 L5
    ALOAD 2
    CHECKCAST okhttp3/OkHttpClient$Builder
   L6
    LINENUMBER 548 L6
    ARETURN
   L7
    LOCALVARIABLE $i$a$-apply-OkHttpClient$Builder$connectionPool$1 I L3 L5 4
    LOCALVARIABLE $this$connectionPool_u24lambda_u241 Lokhttp3/OkHttpClient$Builder; L2 L5 3
    LOCALVARIABLE this Lokhttp3/OkHttpClient$Builder; L0 L7 0
    LOCALVARIABLE connectionPool Lokhttp3/ConnectionPool; L0 L7 1
    MAXSTACK = 2
    MAXLOCALS = 5

  // access flags 0x11
  // signature ()Ljava/util/List<Lokhttp3/Interceptor;>;
  // declaration: java.util.List<okhttp3.Interceptor> interceptors()
  public final interceptors()Ljava/util/List;
  @Lorg/jetbrains/annotations/NotNull;() // invisible
   L0
    LINENUMBER 555 L0
    ALOAD 0
    GETFIELD okhttp3/OkHttpClient$Builder.interceptors : Ljava/util/List;
    ARETURN
   L1
    LOCALVARIABLE this Lokhttp3/OkHttpClient$Builder; L0 L1 0
    MAXSTACK = 1
    MAXLOCALS = 1

  // access flags 0x11
  public final addInterceptor(Lokhttp3/Interceptor;)Lokhttp3/OkHttpClient$Builder;
  @Lorg/jetbrains/annotations/NotNull;() // invisible
    // annotable parameter count: 1 (invisible)
    @Lorg/jetbrains/annotations/NotNull;() // invisible, parameter 0
   L0
    ALOAD 1
    LDC "interceptor"
    INVOKESTATIC kotlin/jvm/internal/Intrinsics.checkNotNullParameter (Ljava/lang/Object;Ljava/lang/String;)V
   L1
    LINENUMBER 557 L1
    ALOAD 0
    ASTORE 2
    ALOAD 2
    CHECKCAST okhttp3/OkHttpClient$Builder
    ASTORE 3
   L2
    ICONST_0
    ISTORE 4
   L3
    LINENUMBER 558 L3
    ALOAD 3
    GETFIELD okhttp3/OkHttpClient$Builder.interceptors : Ljava/util/List;
    CHECKCAST java/util/Collection
    ALOAD 1
    INVOKEINTERFACE java/util/Collection.add (Ljava/lang/Object;)Z (itf)
    POP
   L4
    LINENUMBER 559 L4
    NOP
   L5
    LINENUMBER 557 L5
    ALOAD 2
    CHECKCAST okhttp3/OkHttpClient$Builder
   L6
    LINENUMBER 559 L6
    ARETURN
   L7
    LOCALVARIABLE $i$a$-apply-OkHttpClient$Builder$addInterceptor$1 I L3 L5 4
    LOCALVARIABLE $this$addInterceptor_u24lambda_u242 Lokhttp3/OkHttpClient$Builder; L2 L5 3
    LOCALVARIABLE this Lokhttp3/OkHttpClient$Builder; L0 L7 0
    LOCALVARIABLE interceptor Lokhttp3/Interceptor; L0 L7 1
    MAXSTACK = 2
    MAXLOCALS = 5

  // access flags 0x11
  // signature (Lkotlin/jvm/functions/Function1<-Lokhttp3/Interceptor$Chain;Lokhttp3/Response;>;)Lokhttp3/OkHttpClient$Builder;
  // declaration: okhttp3.OkHttpClient$Builder -addInterceptor(kotlin.jvm.functions.Function1<? super okhttp3.Interceptor$Chain, okhttp3.Response>)
  public final -addInterceptor(Lkotlin/jvm/functions/Function1;)Lokhttp3/OkHttpClient$Builder;
  @Lkotlin/jvm/JvmName;(name="-addInterceptor") // invisible
  @Lorg/jetbrains/annotations/NotNull;() // invisible
    // annotable parameter count: 1 (invisible)
    @Lorg/jetbrains/annotations/NotNull;() // invisible, parameter 0
   L0
    ALOAD 1
    LDC "block"
    INVOKESTATIC kotlin/jvm/internal/Intrinsics.checkNotNullParameter (Ljava/lang/Object;Ljava/lang/String;)V
    ICONST_0
    ISTORE 2
   L1
    LINENUMBER 563 L1
    ALOAD 0
    NEW okhttp3/OkHttpClient$Builder$addInterceptor$2
    DUP
    ALOAD 1
    INVOKESPECIAL okhttp3/OkHttpClient$Builder$addInterceptor$2.<init> (Lkotlin/jvm/functions/Function1;)V
    CHECKCAST okhttp3/Interceptor
    INVOKEVIRTUAL okhttp3/OkHttpClient$Builder.addInterceptor (Lokhttp3/Interceptor;)Lokhttp3/OkHttpClient$Builder;
    ARETURN
   L2
    LOCALVARIABLE $i$f$-addInterceptor I L1 L2 2
    LOCALVARIABLE this Lokhttp3/OkHttpClient$Builder; L0 L2 0
    LOCALVARIABLE block Lkotlin/jvm/functions/Function1; L0 L2 1
    MAXSTACK = 4
    MAXLOCALS = 3

  // access flags 0x11
  // signature ()Ljava/util/List<Lokhttp3/Interceptor;>;
  // declaration: java.util.List<okhttp3.Interceptor> networkInterceptors()
  public final networkInterceptors()Ljava/util/List;
  @Lorg/jetbrains/annotations/NotNull;() // invisible
   L0
    LINENUMBER 570 L0
    ALOAD 0
    GETFIELD okhttp3/OkHttpClient$Builder.networkInterceptors : Ljava/util/List;
    ARETURN
   L1
    LOCALVARIABLE this Lokhttp3/OkHttpClient$Builder; L0 L1 0
    MAXSTACK = 1
    MAXLOCALS = 1

  // access flags 0x11
  public final addNetworkInterceptor(Lokhttp3/Interceptor;)Lokhttp3/OkHttpClient$Builder;
  @Lorg/jetbrains/annotations/NotNull;() // invisible
    // annotable parameter count: 1 (invisible)
    @Lorg/jetbrains/annotations/NotNull;() // invisible, parameter 0
   L0
    ALOAD 1
    LDC "interceptor"
    INVOKESTATIC kotlin/jvm/internal/Intrinsics.checkNotNullParameter (Ljava/lang/Object;Ljava/lang/String;)V
   L1
    LINENUMBER 572 L1
    ALOAD 0
    ASTORE 2
    ALOAD 2
    CHECKCAST okhttp3/OkHttpClient$Builder
    ASTORE 3
   L2
    ICONST_0
    ISTORE 4
   L3
    LINENUMBER 573 L3
    ALOAD 3
    GETFIELD okhttp3/OkHttpClient$Builder.networkInterceptors : Ljava/util/List;
    CHECKCAST java/util/Collection
    ALOAD 1
    INVOKEINTERFACE java/util/Collection.add (Ljava/lang/Object;)Z (itf)
    POP
   L4
    LINENUMBER 574 L4
    NOP
   L5
    LINENUMBER 572 L5
    ALOAD 2
    CHECKCAST okhttp3/OkHttpClient$Builder
   L6
    LINENUMBER 574 L6
    ARETURN
   L7
    LOCALVARIABLE $i$a$-apply-OkHttpClient$Builder$addNetworkInterceptor$1 I L3 L5 4
    LOCALVARIABLE $this$addNetworkInterceptor_u24lambda_u243 Lokhttp3/OkHttpClient$Builder; L2 L5 3
    LOCALVARIABLE this Lokhttp3/OkHttpClient$Builder; L0 L7 0
    LOCALVARIABLE interceptor Lokhttp3/Interceptor; L0 L7 1
    MAXSTACK = 2
    MAXLOCALS = 5

  // access flags 0x11
  // signature (Lkotlin/jvm/functions/Function1<-Lokhttp3/Interceptor$Chain;Lokhttp3/Response;>;)Lokhttp3/OkHttpClient$Builder;
  // declaration: okhttp3.OkHttpClient$Builder -addNetworkInterceptor(kotlin.jvm.functions.Function1<? super okhttp3.Interceptor$Chain, okhttp3.Response>)
  public final -addNetworkInterceptor(Lkotlin/jvm/functions/Function1;)Lokhttp3/OkHttpClient$Builder;
  @Lkotlin/jvm/JvmName;(name="-addNetworkInterceptor") // invisible
  @Lorg/jetbrains/annotations/NotNull;() // invisible
    // annotable parameter count: 1 (invisible)
    @Lorg/jetbrains/annotations/NotNull;() // invisible, parameter 0
   L0
    ALOAD 1
    LDC "block"
    INVOKESTATIC kotlin/jvm/internal/Intrinsics.checkNotNullParameter (Ljava/lang/Object;Ljava/lang/String;)V
    ICONST_0
    ISTORE 2
   L1
    LINENUMBER 578 L1
    ALOAD 0
    NEW okhttp3/OkHttpClient$Builder$addNetworkInterceptor$2
    DUP
    ALOAD 1
    INVOKESPECIAL okhttp3/OkHttpClient$Builder$addNetworkInterceptor$2.<init> (Lkotlin/jvm/functions/Function1;)V
    CHECKCAST okhttp3/Interceptor
    INVOKEVIRTUAL okhttp3/OkHttpClient$Builder.addNetworkInterceptor (Lokhttp3/Interceptor;)Lokhttp3/OkHttpClient$Builder;
    ARETURN
   L2
    LOCALVARIABLE $i$f$-addNetworkInterceptor I L1 L2 2
    LOCALVARIABLE this Lokhttp3/OkHttpClient$Builder; L0 L2 0
    LOCALVARIABLE block Lkotlin/jvm/functions/Function1; L0 L2 1
    MAXSTACK = 4
    MAXLOCALS = 3

  // access flags 0x11
  public final eventListener(Lokhttp3/EventListener;)Lokhttp3/OkHttpClient$Builder;
  @Lorg/jetbrains/annotations/NotNull;() // invisible
    // annotable parameter count: 1 (invisible)
    @Lorg/jetbrains/annotations/NotNull;() // invisible, parameter 0
   L0
    ALOAD 1
    LDC "eventListener"
    INVOKESTATIC kotlin/jvm/internal/Intrinsics.checkNotNullParameter (Ljava/lang/Object;Ljava/lang/String;)V
   L1
    LINENUMBER 586 L1
    ALOAD 0
    ASTORE 2
    ALOAD 2
    CHECKCAST okhttp3/OkHttpClient$Builder
    ASTORE 3
   L2
    ICONST_0
    ISTORE 4
   L3
    LINENUMBER 587 L3
    ALOAD 3
    ALOAD 1
    INVOKESTATIC okhttp3/internal/Util.asFactory (Lokhttp3/EventListener;)Lokhttp3/EventListener$Factory;
    PUTFIELD okhttp3/OkHttpClient$Builder.eventListenerFactory : Lokhttp3/EventListener$Factory;
   L4
    LINENUMBER 588 L4
    NOP
   L5
    LINENUMBER 586 L5
    ALOAD 2
    CHECKCAST okhttp3/OkHttpClient$Builder
   L6
    LINENUMBER 588 L6
    ARETURN
   L7
    LOCALVARIABLE $i$a$-apply-OkHttpClient$Builder$eventListener$1 I L3 L5 4
    LOCALVARIABLE $this$eventListener_u24lambda_u244 Lokhttp3/OkHttpClient$Builder; L2 L5 3
    LOCALVARIABLE this Lokhttp3/OkHttpClient$Builder; L0 L7 0
    LOCALVARIABLE eventListener Lokhttp3/EventListener; L0 L7 1
    MAXSTACK = 2
    MAXLOCALS = 5

  // access flags 0x11
  public final eventListenerFactory(Lokhttp3/EventListener$Factory;)Lokhttp3/OkHttpClient$Builder;
  @Lorg/jetbrains/annotations/NotNull;() // invisible
    // annotable parameter count: 1 (invisible)
    @Lorg/jetbrains/annotations/NotNull;() // invisible, parameter 0
   L0
    ALOAD 1
    LDC "eventListenerFactory"
    INVOKESTATIC kotlin/jvm/internal/Intrinsics.checkNotNullParameter (Ljava/lang/Object;Ljava/lang/String;)V
   L1
    LINENUMBER 596 L1
    ALOAD 0
    ASTORE 2
    ALOAD 2
    CHECKCAST okhttp3/OkHttpClient$Builder
    ASTORE 3
   L2
    ICONST_0
    ISTORE 4
   L3
    LINENUMBER 597 L3
    ALOAD 3
    ALOAD 1
    PUTFIELD okhttp3/OkHttpClient$Builder.eventListenerFactory : Lokhttp3/EventListener$Factory;
   L4
    LINENUMBER 598 L4
    NOP
   L5
    LINENUMBER 596 L5
    ALOAD 2
    CHECKCAST okhttp3/OkHttpClient$Builder
   L6
    LINENUMBER 598 L6
    ARETURN
   L7
    LOCALVARIABLE $i$a$-apply-OkHttpClient$Builder$eventListenerFactory$1 I L3 L5 4
    LOCALVARIABLE $this$eventListenerFactory_u24lambda_u245 Lokhttp3/OkHttpClient$Builder; L2 L5 3
    LOCALVARIABLE this Lokhttp3/OkHttpClient$Builder; L0 L7 0
    LOCALVARIABLE eventListenerFactory Lokhttp3/EventListener$Factory; L0 L7 1
    MAXSTACK = 2
    MAXLOCALS = 5

  // access flags 0x11
  public final retryOnConnectionFailure(Z)Lokhttp3/OkHttpClient$Builder;
  @Lorg/jetbrains/annotations/NotNull;() // invisible
   L0
    LINENUMBER 618 L0
    ALOAD 0
    ASTORE 2
    ALOAD 2
    CHECKCAST okhttp3/OkHttpClient$Builder
    ASTORE 3
   L1
    ICONST_0
    ISTORE 4
   L2
    LINENUMBER 619 L2
    ALOAD 3
    ILOAD 1
    PUTFIELD okhttp3/OkHttpClient$Builder.retryOnConnectionFailure : Z
   L3
    LINENUMBER 620 L3
    NOP
   L4
    LINENUMBER 618 L4
    ALOAD 2
    CHECKCAST okhttp3/OkHttpClient$Builder
   L5
    LINENUMBER 620 L5
    ARETURN
   L6
    LOCALVARIABLE $i$a$-apply-OkHttpClient$Builder$retryOnConnectionFailure$1 I L2 L4 4
    LOCALVARIABLE $this$retryOnConnectionFailure_u24lambda_u246 Lokhttp3/OkHttpClient$Builder; L1 L4 3
    LOCALVARIABLE this Lokhttp3/OkHttpClient$Builder; L0 L6 0
    LOCALVARIABLE retryOnConnectionFailure Z L0 L6 1
    MAXSTACK = 2
    MAXLOCALS = 5

  // access flags 0x11
  public final authenticator(Lokhttp3/Authenticator;)Lokhttp3/OkHttpClient$Builder;
  @Lorg/jetbrains/annotations/NotNull;() // invisible
    // annotable parameter count: 1 (invisible)
    @Lorg/jetbrains/annotations/NotNull;() // invisible, parameter 0
   L0
    ALOAD 1
    LDC "authenticator"
    INVOKESTATIC kotlin/jvm/internal/Intrinsics.checkNotNullParameter (Ljava/lang/Object;Ljava/lang/String;)V
   L1
    LINENUMBER 628 L1
    ALOAD 0
    ASTORE 2
    ALOAD 2
    CHECKCAST okhttp3/OkHttpClient$Builder
    ASTORE 3
   L2
    ICONST_0
    ISTORE 4
   L3
    LINENUMBER 629 L3
    ALOAD 3
    ALOAD 1
    PUTFIELD okhttp3/OkHttpClient$Builder.authenticator : Lokhttp3/Authenticator;
   L4
    LINENUMBER 630 L4
    NOP
   L5
    LINENUMBER 628 L5
    ALOAD 2
    CHECKCAST okhttp3/OkHttpClient$Builder
   L6
    LINENUMBER 630 L6
    ARETURN
   L7
    LOCALVARIABLE $i$a$-apply-OkHttpClient$Builder$authenticator$1 I L3 L5 4
    LOCALVARIABLE $this$authenticator_u24lambda_u247 Lokhttp3/OkHttpClient$Builder; L2 L5 3
    LOCALVARIABLE this Lokhttp3/OkHttpClient$Builder; L0 L7 0
    LOCALVARIABLE authenticator Lokhttp3/Authenticator; L0 L7 1
    MAXSTACK = 2
    MAXLOCALS = 5

  // access flags 0x11
  public final followRedirects(Z)Lokhttp3/OkHttpClient$Builder;
  @Lorg/jetbrains/annotations/NotNull;() // invisible
   L0
    LINENUMBER 633 L0
    ALOAD 0
    ASTORE 2
    ALOAD 2
    CHECKCAST okhttp3/OkHttpClient$Builder
    ASTORE 3
   L1
    ICONST_0
    ISTORE 4
   L2
    LINENUMBER 634 L2
    ALOAD 3
    ILOAD 1
    PUTFIELD okhttp3/OkHttpClient$Builder.followRedirects : Z
   L3
    LINENUMBER 635 L3
    NOP
   L4
    LINENUMBER 633 L4
    ALOAD 2
    CHECKCAST okhttp3/OkHttpClient$Builder
   L5
    LINENUMBER 635 L5
    ARETURN
   L6
    LOCALVARIABLE $i$a$-apply-OkHttpClient$Builder$followRedirects$1 I L2 L4 4
    LOCALVARIABLE $this$followRedirects_u24lambda_u248 Lokhttp3/OkHttpClient$Builder; L1 L4 3
    LOCALVARIABLE this Lokhttp3/OkHttpClient$Builder; L0 L6 0
    LOCALVARIABLE followRedirects Z L0 L6 1
    MAXSTACK = 2
    MAXLOCALS = 5

  // access flags 0x11
  public final followSslRedirects(Z)Lokhttp3/OkHttpClient$Builder;
  @Lorg/jetbrains/annotations/NotNull;() // invisible
   L0
    LINENUMBER 643 L0
    ALOAD 0
    ASTORE 2
    ALOAD 2
    CHECKCAST okhttp3/OkHttpClient$Builder
    ASTORE 3
   L1
    ICONST_0
    ISTORE 4
   L2
    LINENUMBER 644 L2
    ALOAD 3
    ILOAD 1
    PUTFIELD okhttp3/OkHttpClient$Builder.followSslRedirects : Z
   L3
    LINENUMBER 645 L3
    NOP
   L4
    LINENUMBER 643 L4
    ALOAD 2
    CHECKCAST okhttp3/OkHttpClient$Builder
   L5
    LINENUMBER 645 L5
    ARETURN
   L6
    LOCALVARIABLE $i$a$-apply-OkHttpClient$Builder$followSslRedirects$1 I L2 L4 4
    LOCALVARIABLE $this$followSslRedirects_u24lambda_u249 Lokhttp3/OkHttpClient$Builder; L1 L4 3
    LOCALVARIABLE this Lokhttp3/OkHttpClient$Builder; L0 L6 0
    LOCALVARIABLE followProtocolRedirects Z L0 L6 1
    MAXSTACK = 2
    MAXLOCALS = 5

  // access flags 0x11
  public final cookieJar(Lokhttp3/CookieJar;)Lokhttp3/OkHttpClient$Builder;
  @Lorg/jetbrains/annotations/NotNull;() // invisible
    // annotable parameter count: 1 (invisible)
    @Lorg/jetbrains/annotations/NotNull;() // invisible, parameter 0
   L0
    ALOAD 1
    LDC "cookieJar"
    INVOKESTATIC kotlin/jvm/internal/Intrinsics.checkNotNullParameter (Ljava/lang/Object;Ljava/lang/String;)V
   L1
    LINENUMBER 653 L1
    ALOAD 0
    ASTORE 2
    ALOAD 2
    CHECKCAST okhttp3/OkHttpClient$Builder
    ASTORE 3
   L2
    ICONST_0
    ISTORE 4
   L3
    LINENUMBER 654 L3
    ALOAD 3
    ALOAD 1
    PUTFIELD okhttp3/OkHttpClient$Builder.cookieJar : Lokhttp3/CookieJar;
   L4
    LINENUMBER 655 L4
    NOP
   L5
    LINENUMBER 653 L5
    ALOAD 2
    CHECKCAST okhttp3/OkHttpClient$Builder
   L6
    LINENUMBER 655 L6
    ARETURN
   L7
    LOCALVARIABLE $i$a$-apply-OkHttpClient$Builder$cookieJar$1 I L3 L5 4
    LOCALVARIABLE $this$cookieJar_u24lambda_u2410 Lokhttp3/OkHttpClient$Builder; L2 L5 3
    LOCALVARIABLE this Lokhttp3/OkHttpClient$Builder; L0 L7 0
    LOCALVARIABLE cookieJar Lokhttp3/CookieJar; L0 L7 1
    MAXSTACK = 2
    MAXLOCALS = 5

  // access flags 0x11
  public final cache(Lokhttp3/Cache;)Lokhttp3/OkHttpClient$Builder;
  @Lorg/jetbrains/annotations/NotNull;() // invisible
    // annotable parameter count: 1 (invisible)
    @Lorg/jetbrains/annotations/Nullable;() // invisible, parameter 0
   L0
    LINENUMBER 658 L0
    ALOAD 0
    ASTORE 2
    ALOAD 2
    CHECKCAST okhttp3/OkHttpClient$Builder
    ASTORE 3
   L1
    ICONST_0
    ISTORE 4
   L2
    LINENUMBER 659 L2
    ALOAD 3
    ALOAD 1
    PUTFIELD okhttp3/OkHttpClient$Builder.cache : Lokhttp3/Cache;
   L3
    LINENUMBER 660 L3
    NOP
   L4
    LINENUMBER 658 L4
    ALOAD 2
    CHECKCAST okhttp3/OkHttpClient$Builder
   L5
    LINENUMBER 660 L5
    ARETURN
   L6
    LOCALVARIABLE $i$a$-apply-OkHttpClient$Builder$cache$1 I L2 L4 4
    LOCALVARIABLE $this$cache_u24lambda_u2411 Lokhttp3/OkHttpClient$Builder; L1 L4 3
    LOCALVARIABLE this Lokhttp3/OkHttpClient$Builder; L0 L6 0
    LOCALVARIABLE cache Lokhttp3/Cache; L0 L6 1
    MAXSTACK = 2
    MAXLOCALS = 5

  // access flags 0x11
  public final dns(Lokhttp3/Dns;)Lokhttp3/OkHttpClient$Builder;
  @Lorg/jetbrains/annotations/NotNull;() // invisible
    // annotable parameter count: 1 (invisible)
    @Lorg/jetbrains/annotations/NotNull;() // invisible, parameter 0
   L0
    ALOAD 1
    LDC "dns"
    INVOKESTATIC kotlin/jvm/internal/Intrinsics.checkNotNullParameter (Ljava/lang/Object;Ljava/lang/String;)V
   L1
    LINENUMBER 667 L1
    ALOAD 0
    ASTORE 2
    ALOAD 2
    CHECKCAST okhttp3/OkHttpClient$Builder
    ASTORE 3
   L2
    ICONST_0
    ISTORE 4
   L3
    LINENUMBER 668 L3
    ALOAD 1
    ALOAD 3
    GETFIELD okhttp3/OkHttpClient$Builder.dns : Lokhttp3/Dns;
    INVOKESTATIC kotlin/jvm/internal/Intrinsics.areEqual (Ljava/lang/Object;Ljava/lang/Object;)Z
    IFNE L4
   L5
    LINENUMBER 669 L5
    ALOAD 3
    ACONST_NULL
    PUTFIELD okhttp3/OkHttpClient$Builder.routeDatabase : Lokhttp3/internal/connection/RouteDatabase;
   L4
    LINENUMBER 671 L4
   FRAME FULL [okhttp3/OkHttpClient$Builder okhttp3/Dns okhttp3/OkHttpClient$Builder okhttp3/OkHttpClient$Builder I] []
    ALOAD 3
    ALOAD 1
    PUTFIELD okhttp3/OkHttpClient$Builder.dns : Lokhttp3/Dns;
   L6
    LINENUMBER 672 L6
    NOP
   L7
    LINENUMBER 667 L7
    ALOAD 2
    CHECKCAST okhttp3/OkHttpClient$Builder
   L8
    LINENUMBER 672 L8
    ARETURN
   L9
    LOCALVARIABLE $i$a$-apply-OkHttpClient$Builder$dns$1 I L3 L7 4
    LOCALVARIABLE $this$dns_u24lambda_u2412 Lokhttp3/OkHttpClient$Builder; L2 L7 3
    LOCALVARIABLE this Lokhttp3/OkHttpClient$Builder; L0 L9 0
    LOCALVARIABLE dns Lokhttp3/Dns; L0 L9 1
    MAXSTACK = 2
    MAXLOCALS = 5

  // access flags 0x11
  public final proxy(Ljava/net/Proxy;)Lokhttp3/OkHttpClient$Builder;
  @Lorg/jetbrains/annotations/NotNull;() // invisible
    // annotable parameter count: 1 (invisible)
    @Lorg/jetbrains/annotations/Nullable;() // invisible, parameter 0
   L0
    LINENUMBER 679 L0
    ALOAD 0
    ASTORE 2
    ALOAD 2
    CHECKCAST okhttp3/OkHttpClient$Builder
    ASTORE 3
   L1
    ICONST_0
    ISTORE 4
   L2
    LINENUMBER 680 L2
    ALOAD 1
    ALOAD 3
    GETFIELD okhttp3/OkHttpClient$Builder.proxy : Ljava/net/Proxy;
    INVOKESTATIC kotlin/jvm/internal/Intrinsics.areEqual (Ljava/lang/Object;Ljava/lang/Object;)Z
    IFNE L3
   L4
    LINENUMBER 681 L4
    ALOAD 3
    ACONST_NULL
    PUTFIELD okhttp3/OkHttpClient$Builder.routeDatabase : Lokhttp3/internal/connection/RouteDatabase;
   L3
    LINENUMBER 683 L3
   FRAME FULL [okhttp3/OkHttpClient$Builder java/net/Proxy okhttp3/OkHttpClient$Builder okhttp3/OkHttpClient$Builder I] []
    ALOAD 3
    ALOAD 1
    PUTFIELD okhttp3/OkHttpClient$Builder.proxy : Ljava/net/Proxy;
   L5
    LINENUMBER 684 L5
    NOP
   L6
    LINENUMBER 679 L6
    ALOAD 2
    CHECKCAST okhttp3/OkHttpClient$Builder
   L7
    LINENUMBER 684 L7
    ARETURN
   L8
    LOCALVARIABLE $i$a$-apply-OkHttpClient$Builder$proxy$1 I L2 L6 4
    LOCALVARIABLE $this$proxy_u24lambda_u2413 Lokhttp3/OkHttpClient$Builder; L1 L6 3
    LOCALVARIABLE this Lokhttp3/OkHttpClient$Builder; L0 L8 0
    LOCALVARIABLE proxy Ljava/net/Proxy; L0 L8 1
    MAXSTACK = 2
    MAXLOCALS = 5

  // access flags 0x11
  public final proxySelector(Ljava/net/ProxySelector;)Lokhttp3/OkHttpClient$Builder;
  @Lorg/jetbrains/annotations/NotNull;() // invisible
    // annotable parameter count: 1 (invisible)
    @Lorg/jetbrains/annotations/NotNull;() // invisible, parameter 0
   L0
    ALOAD 1
    LDC "proxySelector"
    INVOKESTATIC kotlin/jvm/internal/Intrinsics.checkNotNullParameter (Ljava/lang/Object;Ljava/lang/String;)V
   L1
    LINENUMBER 693 L1
    ALOAD 0
    ASTORE 2
    ALOAD 2
    CHECKCAST okhttp3/OkHttpClient$Builder
    ASTORE 3
   L2
    ICONST_0
    ISTORE 4
   L3
    LINENUMBER 694 L3
    ALOAD 1
    ALOAD 3
    GETFIELD okhttp3/OkHttpClient$Builder.proxySelector : Ljava/net/ProxySelector;
    INVOKESTATIC kotlin/jvm/internal/Intrinsics.areEqual (Ljava/lang/Object;Ljava/lang/Object;)Z
    IFNE L4
   L5
    LINENUMBER 695 L5
    ALOAD 3
    ACONST_NULL
    PUTFIELD okhttp3/OkHttpClient$Builder.routeDatabase : Lokhttp3/internal/connection/RouteDatabase;
   L4
    LINENUMBER 698 L4
   FRAME FULL [okhttp3/OkHttpClient$Builder java/net/ProxySelector okhttp3/OkHttpClient$Builder okhttp3/OkHttpClient$Builder I] []
    ALOAD 3
    ALOAD 1
    PUTFIELD okhttp3/OkHttpClient$Builder.proxySelector : Ljava/net/ProxySelector;
   L6
    LINENUMBER 699 L6
    NOP
   L7
    LINENUMBER 693 L7
    ALOAD 2
    CHECKCAST okhttp3/OkHttpClient$Builder
   L8
    LINENUMBER 699 L8
    ARETURN
   L9
    LOCALVARIABLE $i$a$-apply-OkHttpClient$Builder$proxySelector$1 I L3 L7 4
    LOCALVARIABLE $this$proxySelector_u24lambda_u2414 Lokhttp3/OkHttpClient$Builder; L2 L7 3
    LOCALVARIABLE this Lokhttp3/OkHttpClient$Builder; L0 L9 0
    LOCALVARIABLE proxySelector Ljava/net/ProxySelector; L0 L9 1
    MAXSTACK = 2
    MAXLOCALS = 5

  // access flags 0x11
  public final proxyAuthenticator(Lokhttp3/Authenticator;)Lokhttp3/OkHttpClient$Builder;
  @Lorg/jetbrains/annotations/NotNull;() // invisible
    // annotable parameter count: 1 (invisible)
    @Lorg/jetbrains/annotations/NotNull;() // invisible, parameter 0
   L0
    ALOAD 1
    LDC "proxyAuthenticator"
    INVOKESTATIC kotlin/jvm/internal/Intrinsics.checkNotNullParameter (Ljava/lang/Object;Ljava/lang/String;)V
   L1
    LINENUMBER 707 L1
    ALOAD 0
    ASTORE 2
    ALOAD 2
    CHECKCAST okhttp3/OkHttpClient$Builder
    ASTORE 3
   L2
    ICONST_0
    ISTORE 4
   L3
    LINENUMBER 708 L3
    ALOAD 1
    ALOAD 3
    GETFIELD okhttp3/OkHttpClient$Builder.proxyAuthenticator : Lokhttp3/Authenticator;
    INVOKESTATIC kotlin/jvm/internal/Intrinsics.areEqual (Ljava/lang/Object;Ljava/lang/Object;)Z
    IFNE L4
   L5
    LINENUMBER 709 L5
    ALOAD 3
    ACONST_NULL
    PUTFIELD okhttp3/OkHttpClient$Builder.routeDatabase : Lokhttp3/internal/connection/RouteDatabase;
   L4
    LINENUMBER 712 L4
   FRAME FULL [okhttp3/OkHttpClient$Builder okhttp3/Authenticator okhttp3/OkHttpClient$Builder okhttp3/OkHttpClient$Builder I] []
    ALOAD 3
    ALOAD 1
    PUTFIELD okhttp3/OkHttpClient$Builder.proxyAuthenticator : Lokhttp3/Authenticator;
   L6
    LINENUMBER 713 L6
    NOP
   L7
    LINENUMBER 707 L7
    ALOAD 2
    CHECKCAST okhttp3/OkHttpClient$Builder
   L8
    LINENUMBER 713 L8
    ARETURN
   L9
    LOCALVARIABLE $i$a$-apply-OkHttpClient$Builder$proxyAuthenticator$1 I L3 L7 4
    LOCALVARIABLE $this$proxyAuthenticator_u24lambda_u2415 Lokhttp3/OkHttpClient$Builder; L2 L7 3
    LOCALVARIABLE this Lokhttp3/OkHttpClient$Builder; L0 L9 0
    LOCALVARIABLE proxyAuthenticator Lokhttp3/Authenticator; L0 L9 1
    MAXSTACK = 2
    MAXLOCALS = 5

  // access flags 0x11
  public final socketFactory(Ljavax/net/SocketFactory;)Lokhttp3/OkHttpClient$Builder;
  @Lorg/jetbrains/annotations/NotNull;() // invisible
    // annotable parameter count: 1 (invisible)
    @Lorg/jetbrains/annotations/NotNull;() // invisible, parameter 0
   L0
    ALOAD 1
    LDC "socketFactory"
    INVOKESTATIC kotlin/jvm/internal/Intrinsics.checkNotNullParameter (Ljava/lang/Object;Ljava/lang/String;)V
   L1
    LINENUMBER 722 L1
    ALOAD 0
    ASTORE 2
    ALOAD 2
    CHECKCAST okhttp3/OkHttpClient$Builder
    ASTORE 3
   L2
    ICONST_0
    ISTORE 4
   L3
    LINENUMBER 723 L3
    ALOAD 1
    INSTANCEOF javax/net/ssl/SSLSocketFactory
    IFNE L4
    ICONST_1
    GOTO L5
   L4
   FRAME FULL [okhttp3/OkHttpClient$Builder javax/net/SocketFactory okhttp3/OkHttpClient$Builder okhttp3/OkHttpClient$Builder I] []
    ICONST_0
   L5
   FRAME FULL [okhttp3/OkHttpClient$Builder javax/net/SocketFactory okhttp3/OkHttpClient$Builder okhttp3/OkHttpClient$Builder I] [I]
    IFNE L6
   L7
    LINENUMBER 1080 L7
    ICONST_0
    ISTORE 5
   L8
    LINENUMBER 723 L8
    LDC "socketFactory instanceof SSLSocketFactory"
   L9
    LINENUMBER 723 L9
    ASTORE 5
    NEW java/lang/IllegalArgumentException
    DUP
    ALOAD 5
    INVOKEVIRTUAL java/lang/Object.toString ()Ljava/lang/String;
    INVOKESPECIAL java/lang/IllegalArgumentException.<init> (Ljava/lang/String;)V
    ATHROW
   L6
    LINENUMBER 725 L6
   FRAME FULL [okhttp3/OkHttpClient$Builder javax/net/SocketFactory okhttp3/OkHttpClient$Builder okhttp3/OkHttpClient$Builder I] []
    ALOAD 1
    ALOAD 3
    GETFIELD okhttp3/OkHttpClient$Builder.socketFactory : Ljavax/net/SocketFactory;
    INVOKESTATIC kotlin/jvm/internal/Intrinsics.areEqual (Ljava/lang/Object;Ljava/lang/Object;)Z
    IFNE L10
   L11
    LINENUMBER 726 L11
    ALOAD 3
    ACONST_NULL
    PUTFIELD okhttp3/OkHttpClient$Builder.routeDatabase : Lokhttp3/internal/connection/RouteDatabase;
   L10
    LINENUMBER 729 L10
   FRAME FULL [okhttp3/OkHttpClient$Builder javax/net/SocketFactory okhttp3/OkHttpClient$Builder okhttp3/OkHttpClient$Builder I] []
    ALOAD 3
    ALOAD 1
    PUTFIELD okhttp3/OkHttpClient$Builder.socketFactory : Ljavax/net/SocketFactory;
   L12
    LINENUMBER 730 L12
    NOP
   L13
    LINENUMBER 722 L13
    ALOAD 2
    CHECKCAST okhttp3/OkHttpClient$Builder
   L14
    LINENUMBER 730 L14
    ARETURN
   L15
    LOCALVARIABLE $i$a$-require-OkHttpClient$Builder$socketFactory$1$1 I L8 L9 5
    LOCALVARIABLE $i$a$-apply-OkHttpClient$Builder$socketFactory$1 I L3 L13 4
    LOCALVARIABLE $this$socketFactory_u24lambda_u2417 Lokhttp3/OkHttpClient$Builder; L2 L13 3
    LOCALVARIABLE this Lokhttp3/OkHttpClient$Builder; L0 L15 0
    LOCALVARIABLE socketFactory Ljavax/net/SocketFactory; L0 L15 1
    MAXSTACK = 3
    MAXLOCALS = 6

  // DEPRECATED
  // access flags 0x20011
  public final sslSocketFactory(Ljavax/net/ssl/SSLSocketFactory;)Lokhttp3/OkHttpClient$Builder;
  @Lkotlin/Deprecated;(message="Use the sslSocketFactory overload that accepts a X509TrustManager.", level=Lkotlin/DeprecationLevel;.ERROR)
  @Lorg/jetbrains/annotations/NotNull;() // invisible
    // annotable parameter count: 1 (invisible)
    @Lorg/jetbrains/annotations/NotNull;() // invisible, parameter 0
   L0
    ALOAD 1
    LDC "sslSocketFactory"
    INVOKESTATIC kotlin/jvm/internal/Intrinsics.checkNotNullParameter (Ljava/lang/Object;Ljava/lang/String;)V
   L1
    LINENUMBER 745 L1
    ALOAD 0
    ASTORE 2
    ALOAD 2
    CHECKCAST okhttp3/OkHttpClient$Builder
    ASTORE 3
   L2
    ICONST_0
    ISTORE 4
   L3
    LINENUMBER 746 L3
    ALOAD 1
    ALOAD 3
    GETFIELD okhttp3/OkHttpClient$Builder.sslSocketFactoryOrNull : Ljavax/net/ssl/SSLSocketFactory;
    INVOKESTATIC kotlin/jvm/internal/Intrinsics.areEqual (Ljava/lang/Object;Ljava/lang/Object;)Z
    IFNE L4
   L5
    LINENUMBER 747 L5
    ALOAD 3
    ACONST_NULL
    PUTFIELD okhttp3/OkHttpClient$Builder.routeDatabase : Lokhttp3/internal/connection/RouteDatabase;
   L4
    LINENUMBER 750 L4
   FRAME FULL [okhttp3/OkHttpClient$Builder javax/net/ssl/SSLSocketFactory okhttp3/OkHttpClient$Builder okhttp3/OkHttpClient$Builder I] []
    ALOAD 3
    ALOAD 1
    PUTFIELD okhttp3/OkHttpClient$Builder.sslSocketFactoryOrNull : Ljavax/net/ssl/SSLSocketFactory;
   L6
    LINENUMBER 751 L6
    ALOAD 3
    GETSTATIC okhttp3/internal/platform/Platform.Companion : Lokhttp3/internal/platform/Platform$Companion;
    INVOKEVIRTUAL okhttp3/internal/platform/Platform$Companion.get ()Lokhttp3/internal/platform/Platform;
    ALOAD 1
    INVOKEVIRTUAL okhttp3/internal/platform/Platform.trustManager (Ljavax/net/ssl/SSLSocketFactory;)Ljavax/net/ssl/X509TrustManager;
    DUP
    IFNONNULL L7
    POP
    NEW java/lang/IllegalStateException
    DUP
   L8
    LINENUMBER 752 L8
    NEW java/lang/StringBuilder
    DUP
    INVOKESPECIAL java/lang/StringBuilder.<init> ()V
    LDC "Unable to extract the trust manager on "
    INVOKEVIRTUAL java/lang/StringBuilder.append (Ljava/lang/String;)Ljava/lang/StringBuilder;
    GETSTATIC okhttp3/internal/platform/Platform.Companion : Lokhttp3/internal/platform/Platform$Companion;
    INVOKEVIRTUAL okhttp3/internal/platform/Platform$Companion.get ()Lokhttp3/internal/platform/Platform;
    INVOKEVIRTUAL java/lang/StringBuilder.append (Ljava/lang/Object;)Ljava/lang/StringBuilder;
    LDC ", sslSocketFactory is "
    INVOKEVIRTUAL java/lang/StringBuilder.append (Ljava/lang/String;)Ljava/lang/StringBuilder;
   L9
    LINENUMBER 753 L9
    ALOAD 1
    INVOKEVIRTUAL java/lang/Object.getClass ()Ljava/lang/Class;
   L10
    LINENUMBER 752 L10
    INVOKEVIRTUAL java/lang/StringBuilder.append (Ljava/lang/Object;)Ljava/lang/StringBuilder;
    INVOKEVIRTUAL java/lang/StringBuilder.toString ()Ljava/lang/String;
   L11
    LINENUMBER 751 L11
    INVOKESPECIAL java/lang/IllegalStateException.<init> (Ljava/lang/String;)V
    ATHROW
   L7
   FRAME FULL [okhttp3/OkHttpClient$Builder javax/net/ssl/SSLSocketFactory okhttp3/OkHttpClient$Builder okhttp3/OkHttpClient$Builder I] [okhttp3/OkHttpClient$Builder javax/net/ssl/X509TrustManager]
    PUTFIELD okhttp3/OkHttpClient$Builder.x509TrustManagerOrNull : Ljavax/net/ssl/X509TrustManager;
   L12
    LINENUMBER 754 L12
    ALOAD 3
    GETSTATIC okhttp3/internal/platform/Platform.Companion : Lokhttp3/internal/platform/Platform$Companion;
    INVOKEVIRTUAL okhttp3/internal/platform/Platform$Companion.get ()Lokhttp3/internal/platform/Platform;
    ALOAD 3
    GETFIELD okhttp3/OkHttpClient$Builder.x509TrustManagerOrNull : Ljavax/net/ssl/X509TrustManager;
    DUP
    INVOKESTATIC kotlin/jvm/internal/Intrinsics.checkNotNull (Ljava/lang/Object;)V
    INVOKEVIRTUAL okhttp3/internal/platform/Platform.buildCertificateChainCleaner (Ljavax/net/ssl/X509TrustManager;)Lokhttp3/internal/tls/CertificateChainCleaner;
    PUTFIELD okhttp3/OkHttpClient$Builder.certificateChainCleaner : Lokhttp3/internal/tls/CertificateChainCleaner;
   L13
    LINENUMBER 755 L13
    NOP
   L14
    LINENUMBER 745 L14
    ALOAD 2
    CHECKCAST okhttp3/OkHttpClient$Builder
   L15
    LINENUMBER 755 L15
    ARETURN
   L16
    LOCALVARIABLE $i$a$-apply-OkHttpClient$Builder$sslSocketFactory$1 I L3 L14 4
    LOCALVARIABLE $this$sslSocketFactory_u24lambda_u2418 Lokhttp3/OkHttpClient$Builder; L2 L14 3
    LOCALVARIABLE this Lokhttp3/OkHttpClient$Builder; L0 L16 0
    LOCALVARIABLE sslSocketFactory Ljavax/net/ssl/SSLSocketFactory; L0 L16 1
    MAXSTACK = 5
    MAXLOCALS = 5

  // access flags 0x11
  public final sslSocketFactory(Ljavax/net/ssl/SSLSocketFactory;Ljavax/net/ssl/X509TrustManager;)Lokhttp3/OkHttpClient$Builder;
  @Lorg/jetbrains/annotations/NotNull;() // invisible
    // annotable parameter count: 2 (invisible)
    @Lorg/jetbrains/annotations/NotNull;() // invisible, parameter 0
    @Lorg/jetbrains/annotations/NotNull;() // invisible, parameter 1
   L0
    ALOAD 1
    LDC "sslSocketFactory"
    INVOKESTATIC kotlin/jvm/internal/Intrinsics.checkNotNullParameter (Ljava/lang/Object;Ljava/lang/String;)V
    ALOAD 2
    LDC "trustManager"
    INVOKESTATIC kotlin/jvm/internal/Intrinsics.checkNotNullParameter (Ljava/lang/Object;Ljava/lang/String;)V
   L1
    LINENUMBER 805 L1
    ALOAD 0
    ASTORE 3
    ALOAD 3
    CHECKCAST okhttp3/OkHttpClient$Builder
    ASTORE 4
   L2
    ICONST_0
    ISTORE 5
   L3
    LINENUMBER 806 L3
    ALOAD 1
    ALOAD 4
    GETFIELD okhttp3/OkHttpClient$Builder.sslSocketFactoryOrNull : Ljavax/net/ssl/SSLSocketFactory;
    INVOKESTATIC kotlin/jvm/internal/Intrinsics.areEqual (Ljava/lang/Object;Ljava/lang/Object;)Z
    IFEQ L4
    ALOAD 2
    ALOAD 4
    GETFIELD okhttp3/OkHttpClient$Builder.x509TrustManagerOrNull : Ljavax/net/ssl/X509TrustManager;
    INVOKESTATIC kotlin/jvm/internal/Intrinsics.areEqual (Ljava/lang/Object;Ljava/lang/Object;)Z
    IFNE L5
   L4
    LINENUMBER 807 L4
   FRAME FULL [okhttp3/OkHttpClient$Builder javax/net/ssl/SSLSocketFactory javax/net/ssl/X509TrustManager okhttp3/OkHttpClient$Builder okhttp3/OkHttpClient$Builder I] []
    ALOAD 4
    ACONST_NULL
    PUTFIELD okhttp3/OkHttpClient$Builder.routeDatabase : Lokhttp3/internal/connection/RouteDatabase;
   L5
    LINENUMBER 810 L5
   FRAME FULL [okhttp3/OkHttpClient$Builder javax/net/ssl/SSLSocketFactory javax/net/ssl/X509TrustManager okhttp3/OkHttpClient$Builder okhttp3/OkHttpClient$Builder I] []
    ALOAD 4
    ALOAD 1
    PUTFIELD okhttp3/OkHttpClient$Builder.sslSocketFactoryOrNull : Ljavax/net/ssl/SSLSocketFactory;
   L6
    LINENUMBER 811 L6
    ALOAD 4
    GETSTATIC okhttp3/internal/tls/CertificateChainCleaner.Companion : Lokhttp3/internal/tls/CertificateChainCleaner$Companion;
    ALOAD 2
    INVOKEVIRTUAL okhttp3/internal/tls/CertificateChainCleaner$Companion.get (Ljavax/net/ssl/X509TrustManager;)Lokhttp3/internal/tls/CertificateChainCleaner;
    PUTFIELD okhttp3/OkHttpClient$Builder.certificateChainCleaner : Lokhttp3/internal/tls/CertificateChainCleaner;
   L7
    LINENUMBER 812 L7
    ALOAD 4
    ALOAD 2
    PUTFIELD okhttp3/OkHttpClient$Builder.x509TrustManagerOrNull : Ljavax/net/ssl/X509TrustManager;
   L8
    LINENUMBER 813 L8
    NOP
   L9
    LINENUMBER 805 L9
    ALOAD 3
    CHECKCAST okhttp3/OkHttpClient$Builder
   L10
    LINENUMBER 813 L10
    ARETURN
   L11
    LOCALVARIABLE $i$a$-apply-OkHttpClient$Builder$sslSocketFactory$2 I L3 L9 5
    LOCALVARIABLE $this$sslSocketFactory_u24lambda_u2419 Lokhttp3/OkHttpClient$Builder; L2 L9 4
    LOCALVARIABLE this Lokhttp3/OkHttpClient$Builder; L0 L11 0
    LOCALVARIABLE sslSocketFactory Ljavax/net/ssl/SSLSocketFactory; L0 L11 1
    LOCALVARIABLE trustManager Ljavax/net/ssl/X509TrustManager; L0 L11 2
    MAXSTACK = 3
    MAXLOCALS = 6

  // access flags 0x11
  // signature (Ljava/util/List<Lokhttp3/ConnectionSpec;>;)Lokhttp3/OkHttpClient$Builder;
  // declaration: okhttp3.OkHttpClient$Builder connectionSpecs(java.util.List<okhttp3.ConnectionSpec>)
  public final connectionSpecs(Ljava/util/List;)Lokhttp3/OkHttpClient$Builder;
  @Lorg/jetbrains/annotations/NotNull;() // invisible
    // annotable parameter count: 1 (invisible)
    @Lorg/jetbrains/annotations/NotNull;() // invisible, parameter 0
   L0
    ALOAD 1
    LDC "connectionSpecs"
    INVOKESTATIC kotlin/jvm/internal/Intrinsics.checkNotNullParameter (Ljava/lang/Object;Ljava/lang/String;)V
   L1
    LINENUMBER 815 L1
    ALOAD 0
    ASTORE 2
    ALOAD 2
    CHECKCAST okhttp3/OkHttpClient$Builder
    ASTORE 3
   L2
    ICONST_0
    ISTORE 4
   L3
    LINENUMBER 816 L3
    ALOAD 1
    ALOAD 3
    GETFIELD okhttp3/OkHttpClient$Builder.connectionSpecs : Ljava/util/List;
    INVOKESTATIC kotlin/jvm/internal/Intrinsics.areEqual (Ljava/lang/Object;Ljava/lang/Object;)Z
    IFNE L4
   L5
    LINENUMBER 817 L5
    ALOAD 3
    ACONST_NULL
    PUTFIELD okhttp3/OkHttpClient$Builder.routeDatabase : Lokhttp3/internal/connection/RouteDatabase;
   L4
    LINENUMBER 820 L4
   FRAME FULL [okhttp3/OkHttpClient$Builder java/util/List okhttp3/OkHttpClient$Builder okhttp3/OkHttpClient$Builder I] []
    ALOAD 3
    ALOAD 1
    INVOKESTATIC okhttp3/internal/Util.toImmutableList (Ljava/util/List;)Ljava/util/List;
    PUTFIELD okhttp3/OkHttpClient$Builder.connectionSpecs : Ljava/util/List;
   L6
    LINENUMBER 821 L6
    NOP
   L7
    LINENUMBER 815 L7
    ALOAD 2
    CHECKCAST okhttp3/OkHttpClient$Builder
   L8
    LINENUMBER 821 L8
    ARETURN
   L9
    LOCALVARIABLE $i$a$-apply-OkHttpClient$Builder$connectionSpecs$1 I L3 L7 4
    LOCALVARIABLE $this$connectionSpecs_u24lambda_u2420 Lokhttp3/OkHttpClient$Builder; L2 L7 3
    LOCALVARIABLE this Lokhttp3/OkHttpClient$Builder; L0 L9 0
    LOCALVARIABLE connectionSpecs Ljava/util/List; L0 L9 1
    MAXSTACK = 2
    MAXLOCALS = 5

  // access flags 0x11
  // signature (Ljava/util/List<+Lokhttp3/Protocol;>;)Lokhttp3/OkHttpClient$Builder;
  // declaration: okhttp3.OkHttpClient$Builder protocols(java.util.List<? extends okhttp3.Protocol>)
  public final protocols(Ljava/util/List;)Lokhttp3/OkHttpClient$Builder;
  @Lorg/jetbrains/annotations/NotNull;() // invisible
    // annotable parameter count: 1 (invisible)
    @Lorg/jetbrains/annotations/NotNull;() // invisible, parameter 0
   L0
    ALOAD 1
    LDC "protocols"
    INVOKESTATIC kotlin/jvm/internal/Intrinsics.checkNotNullParameter (Ljava/lang/Object;Ljava/lang/String;)V
   L1
    LINENUMBER 854 L1
    ALOAD 0
    ASTORE 2
    ALOAD 2
    CHECKCAST okhttp3/OkHttpClient$Builder
    ASTORE 3
   L2
    ICONST_0
    ISTORE 4
   L3
    LINENUMBER 856 L3
    ALOAD 1
    CHECKCAST java/util/Collection
    INVOKESTATIC kotlin/collections/CollectionsKt.toMutableList (Ljava/util/Collection;)Ljava/util/List;
    ASTORE 5
   L4
    LINENUMBER 859 L4
    ALOAD 5
    GETSTATIC okhttp3/Protocol.H2_PRIOR_KNOWLEDGE : Lokhttp3/Protocol;
    INVOKEINTERFACE java/util/List.contains (Ljava/lang/Object;)Z (itf)
    IFNE L5
    ALOAD 5
    GETSTATIC okhttp3/Protocol.HTTP_1_1 : Lokhttp3/Protocol;
    INVOKEINTERFACE java/util/List.contains (Ljava/lang/Object;)Z (itf)
    IFEQ L6
   L5
   FRAME FULL [okhttp3/OkHttpClient$Builder java/util/List okhttp3/OkHttpClient$Builder okhttp3/OkHttpClient$Builder I java/util/List] []
    ICONST_1
    GOTO L7
   L6
   FRAME FULL [okhttp3/OkHttpClient$Builder java/util/List okhttp3/OkHttpClient$Builder okhttp3/OkHttpClient$Builder I java/util/List] []
    ICONST_0
   L7
   FRAME FULL [okhttp3/OkHttpClient$Builder java/util/List okhttp3/OkHttpClient$Builder okhttp3/OkHttpClient$Builder I java/util/List] [I]
    IFNE L8
    ICONST_0
    ISTORE 6
   L9
    LINENUMBER 860 L9
    NEW java/lang/StringBuilder
    DUP
    INVOKESPECIAL java/lang/StringBuilder.<init> ()V
    LDC "protocols must contain h2_prior_knowledge or http/1.1: "
    INVOKEVIRTUAL java/lang/StringBuilder.append (Ljava/lang/String;)Ljava/lang/StringBuilder;
    ALOAD 5
    INVOKEVIRTUAL java/lang/StringBuilder.append (Ljava/lang/Object;)Ljava/lang/StringBuilder;
    INVOKEVIRTUAL java/lang/StringBuilder.toString ()Ljava/lang/String;
   L10
    LINENUMBER 859 L10
    ASTORE 6
    NEW java/lang/IllegalArgumentException
    DUP
    ALOAD 6
    INVOKEVIRTUAL java/lang/Object.toString ()Ljava/lang/String;
    INVOKESPECIAL java/lang/IllegalArgumentException.<init> (Ljava/lang/String;)V
    ATHROW
   L8
    LINENUMBER 862 L8
   FRAME FULL [okhttp3/OkHttpClient$Builder java/util/List okhttp3/OkHttpClient$Builder okhttp3/OkHttpClient$Builder I java/util/List] []
    ALOAD 5
    GETSTATIC okhttp3/Protocol.H2_PRIOR_KNOWLEDGE : Lokhttp3/Protocol;
    INVOKEINTERFACE java/util/List.contains (Ljava/lang/Object;)Z (itf)
    IFEQ L11
    ALOAD 5
    INVOKEINTERFACE java/util/List.size ()I (itf)
    ICONST_1
    IF_ICMPGT L12
   L11
   FRAME FULL [okhttp3/OkHttpClient$Builder java/util/List okhttp3/OkHttpClient$Builder okhttp3/OkHttpClient$Builder I java/util/List] []
    ICONST_1
    GOTO L13
   L12
   FRAME FULL [okhttp3/OkHttpClient$Builder java/util/List okhttp3/OkHttpClient$Builder okhttp3/OkHttpClient$Builder I java/util/List] []
    ICONST_0
   L13
   FRAME FULL [okhttp3/OkHttpClient$Builder java/util/List okhttp3/OkHttpClient$Builder okhttp3/OkHttpClient$Builder I java/util/List] [I]
    IFNE L14
    ICONST_0
    ISTORE 6
   L15
    LINENUMBER 863 L15
    NEW java/lang/StringBuilder
    DUP
    INVOKESPECIAL java/lang/StringBuilder.<init> ()V
    LDC "protocols containing h2_prior_knowledge cannot use other protocols: "
    INVOKEVIRTUAL java/lang/StringBuilder.append (Ljava/lang/String;)Ljava/lang/StringBuilder;
    ALOAD 5
    INVOKEVIRTUAL java/lang/StringBuilder.append (Ljava/lang/Object;)Ljava/lang/StringBuilder;
    INVOKEVIRTUAL java/lang/StringBuilder.toString ()Ljava/lang/String;
   L16
    LINENUMBER 862 L16
    ASTORE 6
    NEW java/lang/IllegalArgumentException
    DUP
    ALOAD 6
    INVOKEVIRTUAL java/lang/Object.toString ()Ljava/lang/String;
    INVOKESPECIAL java/lang/IllegalArgumentException.<init> (Ljava/lang/String;)V
    ATHROW
   L14
    LINENUMBER 865 L14
   FRAME FULL [okhttp3/OkHttpClient$Builder java/util/List okhttp3/OkHttpClient$Builder okhttp3/OkHttpClient$Builder I java/util/List] []
    ALOAD 5
    GETSTATIC okhttp3/Protocol.HTTP_1_0 : Lokhttp3/Protocol;
    INVOKEINTERFACE java/util/List.contains (Ljava/lang/Object;)Z (itf)
    IFNE L17
    ICONST_1
    GOTO L18
   L17
   FRAME FULL [okhttp3/OkHttpClient$Builder java/util/List okhttp3/OkHttpClient$Builder okhttp3/OkHttpClient$Builder I java/util/List] []
    ICONST_0
   L18
   FRAME FULL [okhttp3/OkHttpClient$Builder java/util/List okhttp3/OkHttpClient$Builder okhttp3/OkHttpClient$Builder I java/util/List] [I]
    IFNE L19
    ICONST_0
    ISTORE 6
   L20
    LINENUMBER 866 L20
    NEW java/lang/StringBuilder
    DUP
    INVOKESPECIAL java/lang/StringBuilder.<init> ()V
    LDC "protocols must not contain http/1.0: "
    INVOKEVIRTUAL java/lang/StringBuilder.append (Ljava/lang/String;)Ljava/lang/StringBuilder;
    ALOAD 5
    INVOKEVIRTUAL java/lang/StringBuilder.append (Ljava/lang/Object;)Ljava/lang/StringBuilder;
    INVOKEVIRTUAL java/lang/StringBuilder.toString ()Ljava/lang/String;
   L21
    LINENUMBER 865 L21
    ASTORE 6
    NEW java/lang/IllegalArgumentException
    DUP
    ALOAD 6
    INVOKEVIRTUAL java/lang/Object.toString ()Ljava/lang/String;
    INVOKESPECIAL java/lang/IllegalArgumentException.<init> (Ljava/lang/String;)V
    ATHROW
   L19
    LINENUMBER 868 L19
   FRAME FULL [okhttp3/OkHttpClient$Builder java/util/List okhttp3/OkHttpClient$Builder okhttp3/OkHttpClient$Builder I java/util/List] []
    ALOAD 5
    LDC "null cannot be cast to non-null type kotlin.collections.List<okhttp3.Protocol?>"
    INVOKESTATIC kotlin/jvm/internal/Intrinsics.checkNotNull (Ljava/lang/Object;Ljava/lang/String;)V
    ALOAD 5
    ACONST_NULL
    INVOKEINTERFACE java/util/List.contains (Ljava/lang/Object;)Z (itf)
    IFNE L22
    ICONST_1
    GOTO L23
   L22
   FRAME FULL [okhttp3/OkHttpClient$Builder java/util/List okhttp3/OkHttpClient$Builder okhttp3/OkHttpClient$Builder I java/util/List] []
    ICONST_0
   L23
   FRAME FULL [okhttp3/OkHttpClient$Builder java/util/List okhttp3/OkHttpClient$Builder okhttp3/OkHttpClient$Builder I java/util/List] [I]
    IFNE L24
    ICONST_0
    ISTORE 6
   L25
    LINENUMBER 869 L25
    LDC "protocols must not contain null"
   L26
    LINENUMBER 868 L26
    ASTORE 6
    NEW java/lang/IllegalArgumentException
    DUP
    ALOAD 6
    INVOKEVIRTUAL java/lang/Object.toString ()Ljava/lang/String;
    INVOKESPECIAL java/lang/IllegalArgumentException.<init> (Ljava/lang/String;)V
    ATHROW
   L24
    LINENUMBER 874 L24
   FRAME FULL [okhttp3/OkHttpClient$Builder java/util/List okhttp3/OkHttpClient$Builder okhttp3/OkHttpClient$Builder I java/util/List] []
    ALOAD 5
    GETSTATIC okhttp3/Protocol.SPDY_3 : Lokhttp3/Protocol;
    INVOKEINTERFACE java/util/List.remove (Ljava/lang/Object;)Z (itf)
    POP
   L27
    LINENUMBER 876 L27
    ALOAD 5
    ALOAD 3
    GETFIELD okhttp3/OkHttpClient$Builder.protocols : Ljava/util/List;
    INVOKESTATIC kotlin/jvm/internal/Intrinsics.areEqual (Ljava/lang/Object;Ljava/lang/Object;)Z
    IFNE L28
   L29
    LINENUMBER 877 L29
    ALOAD 3
    ACONST_NULL
    PUTFIELD okhttp3/OkHttpClient$Builder.routeDatabase : Lokhttp3/internal/connection/RouteDatabase;
   L28
    LINENUMBER 881 L28
   FRAME FULL [okhttp3/OkHttpClient$Builder java/util/List okhttp3/OkHttpClient$Builder okhttp3/OkHttpClient$Builder I java/util/List] []
    ALOAD 3
    ALOAD 5
    INVOKESTATIC java/util/Collections.unmodifiableList (Ljava/util/List;)Ljava/util/List;
    DUP
    LDC "unmodifiableList(protocolsCopy)"
    INVOKESTATIC kotlin/jvm/internal/Intrinsics.checkNotNullExpressionValue (Ljava/lang/Object;Ljava/lang/String;)V
    PUTFIELD okhttp3/OkHttpClient$Builder.protocols : Ljava/util/List;
   L30
    LINENUMBER 882 L30
    NOP
   L31
    LINENUMBER 854 L31
    ALOAD 2
    CHECKCAST okhttp3/OkHttpClient$Builder
   L32
    LINENUMBER 882 L32
    ARETURN
   L33
    LOCALVARIABLE $i$a$-require-OkHttpClient$Builder$protocols$1$1 I L9 L10 6
    LOCALVARIABLE $i$a$-require-OkHttpClient$Builder$protocols$1$2 I L15 L16 6
    LOCALVARIABLE $i$a$-require-OkHttpClient$Builder$protocols$1$3 I L20 L21 6
    LOCALVARIABLE $i$a$-require-OkHttpClient$Builder$protocols$1$4 I L25 L26 6
    LOCALVARIABLE $i$a$-apply-OkHttpClient$Builder$protocols$1 I L3 L31 4
    LOCALVARIABLE protocolsCopy Ljava/util/List; L4 L31 5
    LOCALVARIABLE $this$protocols_u24lambda_u2425 Lokhttp3/OkHttpClient$Builder; L2 L31 3
    LOCALVARIABLE this Lokhttp3/OkHttpClient$Builder; L0 L33 0
    LOCALVARIABLE protocols Ljava/util/List; L0 L33 1
    MAXSTACK = 4
    MAXLOCALS = 7

  // access flags 0x11
  public final hostnameVerifier(Ljavax/net/ssl/HostnameVerifier;)Lokhttp3/OkHttpClient$Builder;
  @Lorg/jetbrains/annotations/NotNull;() // invisible
    // annotable parameter count: 1 (invisible)
    @Lorg/jetbrains/annotations/NotNull;() // invisible, parameter 0
   L0
    ALOAD 1
    LDC "hostnameVerifier"
    INVOKESTATIC kotlin/jvm/internal/Intrinsics.checkNotNullParameter (Ljava/lang/Object;Ljava/lang/String;)V
   L1
    LINENUMBER 890 L1
    ALOAD 0
    ASTORE 2
    ALOAD 2
    CHECKCAST okhttp3/OkHttpClient$Builder
    ASTORE 3
   L2
    ICONST_0
    ISTORE 4
   L3
    LINENUMBER 891 L3
    ALOAD 1
    ALOAD 3
    GETFIELD okhttp3/OkHttpClient$Builder.hostnameVerifier : Ljavax/net/ssl/HostnameVerifier;
    INVOKESTATIC kotlin/jvm/internal/Intrinsics.areEqual (Ljava/lang/Object;Ljava/lang/Object;)Z
    IFNE L4
   L5
    LINENUMBER 892 L5
    ALOAD 3
    ACONST_NULL
    PUTFIELD okhttp3/OkHttpClient$Builder.routeDatabase : Lokhttp3/internal/connection/RouteDatabase;
   L4
    LINENUMBER 895 L4
   FRAME FULL [okhttp3/OkHttpClient$Builder javax/net/ssl/HostnameVerifier okhttp3/OkHttpClient$Builder okhttp3/OkHttpClient$Builder I] []
    ALOAD 3
    ALOAD 1
    PUTFIELD okhttp3/OkHttpClient$Builder.hostnameVerifier : Ljavax/net/ssl/HostnameVerifier;
   L6
    LINENUMBER 896 L6
    NOP
   L7
    LINENUMBER 890 L7
    ALOAD 2
    CHECKCAST okhttp3/OkHttpClient$Builder
   L8
    LINENUMBER 896 L8
    ARETURN
   L9
    LOCALVARIABLE $i$a$-apply-OkHttpClient$Builder$hostnameVerifier$1 I L3 L7 4
    LOCALVARIABLE $this$hostnameVerifier_u24lambda_u2426 Lokhttp3/OkHttpClient$Builder; L2 L7 3
    LOCALVARIABLE this Lokhttp3/OkHttpClient$Builder; L0 L9 0
    LOCALVARIABLE hostnameVerifier Ljavax/net/ssl/HostnameVerifier; L0 L9 1
    MAXSTACK = 2
    MAXLOCALS = 5

  // access flags 0x11
  public final certificatePinner(Lokhttp3/CertificatePinner;)Lokhttp3/OkHttpClient$Builder;
  @Lorg/jetbrains/annotations/NotNull;() // invisible
    // annotable parameter count: 1 (invisible)
    @Lorg/jetbrains/annotations/NotNull;() // invisible, parameter 0
   L0
    ALOAD 1
    LDC "certificatePinner"
    INVOKESTATIC kotlin/jvm/internal/Intrinsics.checkNotNullParameter (Ljava/lang/Object;Ljava/lang/String;)V
   L1
    LINENUMBER 903 L1
    ALOAD 0
    ASTORE 2
    ALOAD 2
    CHECKCAST okhttp3/OkHttpClient$Builder
    ASTORE 3
   L2
    ICONST_0
    ISTORE 4
   L3
    LINENUMBER 904 L3
    ALOAD 1
    ALOAD 3
    GETFIELD okhttp3/OkHttpClient$Builder.certificatePinner : Lokhttp3/CertificatePinner;
    INVOKESTATIC kotlin/jvm/internal/Intrinsics.areEqual (Ljava/lang/Object;Ljava/lang/Object;)Z
    IFNE L4
   L5
    LINENUMBER 905 L5
    ALOAD 3
    ACONST_NULL
    PUTFIELD okhttp3/OkHttpClient$Builder.routeDatabase : Lokhttp3/internal/connection/RouteDatabase;
   L4
    LINENUMBER 908 L4
   FRAME FULL [okhttp3/OkHttpClient$Builder okhttp3/CertificatePinner okhttp3/OkHttpClient$Builder okhttp3/OkHttpClient$Builder I] []
    ALOAD 3
    ALOAD 1
    PUTFIELD okhttp3/OkHttpClient$Builder.certificatePinner : Lokhttp3/CertificatePinner;
   L6
    LINENUMBER 909 L6
    NOP
   L7
    LINENUMBER 903 L7
    ALOAD 2
    CHECKCAST okhttp3/OkHttpClient$Builder
   L8
    LINENUMBER 909 L8
    ARETURN
   L9
    LOCALVARIABLE $i$a$-apply-OkHttpClient$Builder$certificatePinner$1 I L3 L7 4
    LOCALVARIABLE $this$certificatePinner_u24lambda_u2427 Lokhttp3/OkHttpClient$Builder; L2 L7 3
    LOCALVARIABLE this Lokhttp3/OkHttpClient$Builder; L0 L9 0
    LOCALVARIABLE certificatePinner Lokhttp3/CertificatePinner; L0 L9 1
    MAXSTACK = 2
    MAXLOCALS = 5

  // access flags 0x11
  public final callTimeout(JLjava/util/concurrent/TimeUnit;)Lokhttp3/OkHttpClient$Builder;
  @Lorg/jetbrains/annotations/NotNull;() // invisible
    // annotable parameter count: 2 (invisible)
    @Lorg/jetbrains/annotations/NotNull;() // invisible, parameter 1
   L0
    ALOAD 3
    LDC "unit"
    INVOKESTATIC kotlin/jvm/internal/Intrinsics.checkNotNullParameter (Ljava/lang/Object;Ljava/lang/String;)V
   L1
    LINENUMBER 921 L1
    ALOAD 0
    ASTORE 4
    ALOAD 4
    CHECKCAST okhttp3/OkHttpClient$Builder
    ASTORE 5
   L2
    ICONST_0
    ISTORE 6
   L3
    LINENUMBER 922 L3
    ALOAD 5
    LDC "timeout"
    LLOAD 1
    ALOAD 3
    INVOKESTATIC okhttp3/internal/Util.checkDuration (Ljava/lang/String;JLjava/util/concurrent/TimeUnit;)I
    PUTFIELD okhttp3/OkHttpClient$Builder.callTimeout : I
   L4
    LINENUMBER 923 L4
    NOP
   L5
    LINENUMBER 921 L5
    ALOAD 4
    CHECKCAST okhttp3/OkHttpClient$Builder
   L6
    LINENUMBER 923 L6
    ARETURN
   L7
    LOCALVARIABLE $i$a$-apply-OkHttpClient$Builder$callTimeout$1 I L3 L5 6
    LOCALVARIABLE $this$callTimeout_u24lambda_u2428 Lokhttp3/OkHttpClient$Builder; L2 L5 5
    LOCALVARIABLE this Lokhttp3/OkHttpClient$Builder; L0 L7 0
    LOCALVARIABLE timeout J L0 L7 1
    LOCALVARIABLE unit Ljava/util/concurrent/TimeUnit; L0 L7 3
    MAXSTACK = 5
    MAXLOCALS = 7

  // access flags 0x11
  public final callTimeout(Ljava/time/Duration;)Lokhttp3/OkHttpClient$Builder;
  @Lorg/codehaus/mojo/animal_sniffer/IgnoreJRERequirement;() // invisible
  @Lorg/jetbrains/annotations/NotNull;() // invisible
    // annotable parameter count: 1 (invisible)
    @Lorg/jetbrains/annotations/NotNull;() // invisible, parameter 0
   L0
    ALOAD 1
    LDC "duration"
    INVOKESTATIC kotlin/jvm/internal/Intrinsics.checkNotNullParameter (Ljava/lang/Object;Ljava/lang/String;)V
   L1
    LINENUMBER 936 L1
    ALOAD 0
    ASTORE 2
    ALOAD 2
    CHECKCAST okhttp3/OkHttpClient$Builder
    ASTORE 3
   L2
    ICONST_0
    ISTORE 4
   L3
    LINENUMBER 937 L3
    ALOAD 3
    ALOAD 1
    INVOKEVIRTUAL java/time/Duration.toMillis ()J
    GETSTATIC java/util/concurrent/TimeUnit.MILLISECONDS : Ljava/util/concurrent/TimeUnit;
    INVOKEVIRTUAL okhttp3/OkHttpClient$Builder.callTimeout (JLjava/util/concurrent/TimeUnit;)Lokhttp3/OkHttpClient$Builder;
    POP
   L4
    LINENUMBER 938 L4
    NOP
   L5
    LINENUMBER 936 L5
    ALOAD 2
    CHECKCAST okhttp3/OkHttpClient$Builder
   L6
    LINENUMBER 938 L6
    ARETURN
   L7
    LOCALVARIABLE $i$a$-apply-OkHttpClient$Builder$callTimeout$2 I L3 L5 4
    LOCALVARIABLE $this$callTimeout_u24lambda_u2429 Lokhttp3/OkHttpClient$Builder; L2 L5 3
    LOCALVARIABLE this Lokhttp3/OkHttpClient$Builder; L0 L7 0
    LOCALVARIABLE duration Ljava/time/Duration; L0 L7 1
    MAXSTACK = 4
    MAXLOCALS = 5

  // access flags 0x11
  public final connectTimeout(JLjava/util/concurrent/TimeUnit;)Lokhttp3/OkHttpClient$Builder;
  @Lorg/jetbrains/annotations/NotNull;() // invisible
    // annotable parameter count: 2 (invisible)
    @Lorg/jetbrains/annotations/NotNull;() // invisible, parameter 1
   L0
    ALOAD 3
    LDC "unit"
    INVOKESTATIC kotlin/jvm/internal/Intrinsics.checkNotNullParameter (Ljava/lang/Object;Ljava/lang/String;)V
   L1
    LINENUMBER 947 L1
    ALOAD 0
    ASTORE 4
    ALOAD 4
    CHECKCAST okhttp3/OkHttpClient$Builder
    ASTORE 5
   L2
    ICONST_0
    ISTORE 6
   L3
    LINENUMBER 948 L3
    ALOAD 5
    LDC "timeout"
    LLOAD 1
    ALOAD 3
    INVOKESTATIC okhttp3/internal/Util.checkDuration (Ljava/lang/String;JLjava/util/concurrent/TimeUnit;)I
    PUTFIELD okhttp3/OkHttpClient$Builder.connectTimeout : I
   L4
    LINENUMBER 949 L4
    NOP
   L5
    LINENUMBER 947 L5
    ALOAD 4
    CHECKCAST okhttp3/OkHttpClient$Builder
   L6
    LINENUMBER 949 L6
    ARETURN
   L7
    LOCALVARIABLE $i$a$-apply-OkHttpClient$Builder$connectTimeout$1 I L3 L5 6
    LOCALVARIABLE $this$connectTimeout_u24lambda_u2430 Lokhttp3/OkHttpClient$Builder; L2 L5 5
    LOCALVARIABLE this Lokhttp3/OkHttpClient$Builder; L0 L7 0
    LOCALVARIABLE timeout J L0 L7 1
    LOCALVARIABLE unit Ljava/util/concurrent/TimeUnit; L0 L7 3
    MAXSTACK = 5
    MAXLOCALS = 7

  // access flags 0x11
  public final connectTimeout(Ljava/time/Duration;)Lokhttp3/OkHttpClient$Builder;
  @Lorg/codehaus/mojo/animal_sniffer/IgnoreJRERequirement;() // invisible
  @Lorg/jetbrains/annotations/NotNull;() // invisible
    // annotable parameter count: 1 (invisible)
    @Lorg/jetbrains/annotations/NotNull;() // invisible, parameter 0
   L0
    ALOAD 1
    LDC "duration"
    INVOKESTATIC kotlin/jvm/internal/Intrinsics.checkNotNullParameter (Ljava/lang/Object;Ljava/lang/String;)V
   L1
    LINENUMBER 959 L1
    ALOAD 0
    ASTORE 2
    ALOAD 2
    CHECKCAST okhttp3/OkHttpClient$Builder
    ASTORE 3
   L2
    ICONST_0
    ISTORE 4
   L3
    LINENUMBER 960 L3
    ALOAD 3
    ALOAD 1
    INVOKEVIRTUAL java/time/Duration.toMillis ()J
    GETSTATIC java/util/concurrent/TimeUnit.MILLISECONDS : Ljava/util/concurrent/TimeUnit;
    INVOKEVIRTUAL okhttp3/OkHttpClient$Builder.connectTimeout (JLjava/util/concurrent/TimeUnit;)Lokhttp3/OkHttpClient$Builder;
    POP
   L4
    LINENUMBER 961 L4
    NOP
   L5
    LINENUMBER 959 L5
    ALOAD 2
    CHECKCAST okhttp3/OkHttpClient$Builder
   L6
    LINENUMBER 961 L6
    ARETURN
   L7
    LOCALVARIABLE $i$a$-apply-OkHttpClient$Builder$connectTimeout$2 I L3 L5 4
    LOCALVARIABLE $this$connectTimeout_u24lambda_u2431 Lokhttp3/OkHttpClient$Builder; L2 L5 3
    LOCALVARIABLE this Lokhttp3/OkHttpClient$Builder; L0 L7 0
    LOCALVARIABLE duration Ljava/time/Duration; L0 L7 1
    MAXSTACK = 4
    MAXLOCALS = 5

  // access flags 0x11
  public final readTimeout(JLjava/util/concurrent/TimeUnit;)Lokhttp3/OkHttpClient$Builder;
  @Lorg/jetbrains/annotations/NotNull;() // invisible
    // annotable parameter count: 2 (invisible)
    @Lorg/jetbrains/annotations/NotNull;() // invisible, parameter 1
   L0
    ALOAD 3
    LDC "unit"
    INVOKESTATIC kotlin/jvm/internal/Intrinsics.checkNotNullParameter (Ljava/lang/Object;Ljava/lang/String;)V
   L1
    LINENUMBER 973 L1
    ALOAD 0
    ASTORE 4
    ALOAD 4
    CHECKCAST okhttp3/OkHttpClient$Builder
    ASTORE 5
   L2
    ICONST_0
    ISTORE 6
   L3
    LINENUMBER 974 L3
    ALOAD 5
    LDC "timeout"
    LLOAD 1
    ALOAD 3
    INVOKESTATIC okhttp3/internal/Util.checkDuration (Ljava/lang/String;JLjava/util/concurrent/TimeUnit;)I
    PUTFIELD okhttp3/OkHttpClient$Builder.readTimeout : I
   L4
    LINENUMBER 975 L4
    NOP
   L5
    LINENUMBER 973 L5
    ALOAD 4
    CHECKCAST okhttp3/OkHttpClient$Builder
   L6
    LINENUMBER 975 L6
    ARETURN
   L7
    LOCALVARIABLE $i$a$-apply-OkHttpClient$Builder$readTimeout$1 I L3 L5 6
    LOCALVARIABLE $this$readTimeout_u24lambda_u2432 Lokhttp3/OkHttpClient$Builder; L2 L5 5
    LOCALVARIABLE this Lokhttp3/OkHttpClient$Builder; L0 L7 0
    LOCALVARIABLE timeout J L0 L7 1
    LOCALVARIABLE unit Ljava/util/concurrent/TimeUnit; L0 L7 3
    MAXSTACK = 5
    MAXLOCALS = 7

  // access flags 0x11
  public final readTimeout(Ljava/time/Duration;)Lokhttp3/OkHttpClient$Builder;
  @Lorg/codehaus/mojo/animal_sniffer/IgnoreJRERequirement;() // invisible
  @Lorg/jetbrains/annotations/NotNull;() // invisible
    // annotable parameter count: 1 (invisible)
    @Lorg/jetbrains/annotations/NotNull;() // invisible, parameter 0
   L0
    ALOAD 1
    LDC "duration"
    INVOKESTATIC kotlin/jvm/internal/Intrinsics.checkNotNullParameter (Ljava/lang/Object;Ljava/lang/String;)V
   L1
    LINENUMBER 988 L1
    ALOAD 0
    ASTORE 2
    ALOAD 2
    CHECKCAST okhttp3/OkHttpClient$Builder
    ASTORE 3
   L2
    ICONST_0
    ISTORE 4
   L3
    LINENUMBER 989 L3
    ALOAD 3
    ALOAD 1
    INVOKEVIRTUAL java/time/Duration.toMillis ()J
    GETSTATIC java/util/concurrent/TimeUnit.MILLISECONDS : Ljava/util/concurrent/TimeUnit;
    INVOKEVIRTUAL okhttp3/OkHttpClient$Builder.readTimeout (JLjava/util/concurrent/TimeUnit;)Lokhttp3/OkHttpClient$Builder;
    POP
   L4
    LINENUMBER 990 L4
    NOP
   L5
    LINENUMBER 988 L5
    ALOAD 2
    CHECKCAST okhttp3/OkHttpClient$Builder
   L6
    LINENUMBER 990 L6
    ARETURN
   L7
    LOCALVARIABLE $i$a$-apply-OkHttpClient$Builder$readTimeout$2 I L3 L5 4
    LOCALVARIABLE $this$readTimeout_u24lambda_u2433 Lokhttp3/OkHttpClient$Builder; L2 L5 3
    LOCALVARIABLE this Lokhttp3/OkHttpClient$Builder; L0 L7 0
    LOCALVARIABLE duration Ljava/time/Duration; L0 L7 1
    MAXSTACK = 4
    MAXLOCALS = 5

  // access flags 0x11
  public final writeTimeout(JLjava/util/concurrent/TimeUnit;)Lokhttp3/OkHttpClient$Builder;
  @Lorg/jetbrains/annotations/NotNull;() // invisible
    // annotable parameter count: 2 (invisible)
    @Lorg/jetbrains/annotations/NotNull;() // invisible, parameter 1
   L0
    ALOAD 3
    LDC "unit"
    INVOKESTATIC kotlin/jvm/internal/Intrinsics.checkNotNullParameter (Ljava/lang/Object;Ljava/lang/String;)V
   L1
    LINENUMBER 1001 L1
    ALOAD 0
    ASTORE 4
    ALOAD 4
    CHECKCAST okhttp3/OkHttpClient$Builder
    ASTORE 5
   L2
    ICONST_0
    ISTORE 6
   L3
    LINENUMBER 1002 L3
    ALOAD 5
    LDC "timeout"
    LLOAD 1
    ALOAD 3
    INVOKESTATIC okhttp3/internal/Util.checkDuration (Ljava/lang/String;JLjava/util/concurrent/TimeUnit;)I
    PUTFIELD okhttp3/OkHttpClient$Builder.writeTimeout : I
   L4
    LINENUMBER 1003 L4
    NOP
   L5
    LINENUMBER 1001 L5
    ALOAD 4
    CHECKCAST okhttp3/OkHttpClient$Builder
   L6
    LINENUMBER 1003 L6
    ARETURN
   L7
    LOCALVARIABLE $i$a$-apply-OkHttpClient$Builder$writeTimeout$1 I L3 L5 6
    LOCALVARIABLE $this$writeTimeout_u24lambda_u2434 Lokhttp3/OkHttpClient$Builder; L2 L5 5
    LOCALVARIABLE this Lokhttp3/OkHttpClient$Builder; L0 L7 0
    LOCALVARIABLE timeout J L0 L7 1
    LOCALVARIABLE unit Ljava/util/concurrent/TimeUnit; L0 L7 3
    MAXSTACK = 5
    MAXLOCALS = 7

  // access flags 0x11
  public final writeTimeout(Ljava/time/Duration;)Lokhttp3/OkHttpClient$Builder;
  @Lorg/codehaus/mojo/animal_sniffer/IgnoreJRERequirement;() // invisible
  @Lorg/jetbrains/annotations/NotNull;() // invisible
    // annotable parameter count: 1 (invisible)
    @Lorg/jetbrains/annotations/NotNull;() // invisible, parameter 0
   L0
    ALOAD 1
    LDC "duration"
    INVOKESTATIC kotlin/jvm/internal/Intrinsics.checkNotNullParameter (Ljava/lang/Object;Ljava/lang/String;)V
   L1
    LINENUMBER 1015 L1
    ALOAD 0
    ASTORE 2
    ALOAD 2
    CHECKCAST okhttp3/OkHttpClient$Builder
    ASTORE 3
   L2
    ICONST_0
    ISTORE 4
   L3
    LINENUMBER 1016 L3
    ALOAD 3
    ALOAD 1
    INVOKEVIRTUAL java/time/Duration.toMillis ()J
    GETSTATIC java/util/concurrent/TimeUnit.MILLISECONDS : Ljava/util/concurrent/TimeUnit;
    INVOKEVIRTUAL okhttp3/OkHttpClient$Builder.writeTimeout (JLjava/util/concurrent/TimeUnit;)Lokhttp3/OkHttpClient$Builder;
    POP
   L4
    LINENUMBER 1017 L4
    NOP
   L5
    LINENUMBER 1015 L5
    ALOAD 2
    CHECKCAST okhttp3/OkHttpClient$Builder
   L6
    LINENUMBER 1017 L6
    ARETURN
   L7
    LOCALVARIABLE $i$a$-apply-OkHttpClient$Builder$writeTimeout$2 I L3 L5 4
    LOCALVARIABLE $this$writeTimeout_u24lambda_u2435 Lokhttp3/OkHttpClient$Builder; L2 L5 3
    LOCALVARIABLE this Lokhttp3/OkHttpClient$Builder; L0 L7 0
    LOCALVARIABLE duration Ljava/time/Duration; L0 L7 1
    MAXSTACK = 4
    MAXLOCALS = 5

  // access flags 0x11
  public final pingInterval(JLjava/util/concurrent/TimeUnit;)Lokhttp3/OkHttpClient$Builder;
  @Lorg/jetbrains/annotations/NotNull;() // invisible
    // annotable parameter count: 2 (invisible)
    @Lorg/jetbrains/annotations/NotNull;() // invisible, parameter 1
   L0
    ALOAD 3
    LDC "unit"
    INVOKESTATIC kotlin/jvm/internal/Intrinsics.checkNotNullParameter (Ljava/lang/Object;Ljava/lang/String;)V
   L1
    LINENUMBER 1032 L1
    ALOAD 0
    ASTORE 4
    ALOAD 4
    CHECKCAST okhttp3/OkHttpClient$Builder
    ASTORE 5
   L2
    ICONST_0
    ISTORE 6
   L3
    LINENUMBER 1033 L3
    ALOAD 5
    LDC "interval"
    LLOAD 1
    ALOAD 3
    INVOKESTATIC okhttp3/internal/Util.checkDuration (Ljava/lang/String;JLjava/util/concurrent/TimeUnit;)I
    PUTFIELD okhttp3/OkHttpClient$Builder.pingInterval : I
   L4
    LINENUMBER 1034 L4
    NOP
   L5
    LINENUMBER 1032 L5
    ALOAD 4
    CHECKCAST okhttp3/OkHttpClient$Builder
   L6
    LINENUMBER 1034 L6
    ARETURN
   L7
    LOCALVARIABLE $i$a$-apply-OkHttpClient$Builder$pingInterval$1 I L3 L5 6
    LOCALVARIABLE $this$pingInterval_u24lambda_u2436 Lokhttp3/OkHttpClient$Builder; L2 L5 5
    LOCALVARIABLE this Lokhttp3/OkHttpClient$Builder; L0 L7 0
    LOCALVARIABLE interval J L0 L7 1
    LOCALVARIABLE unit Ljava/util/concurrent/TimeUnit; L0 L7 3
    MAXSTACK = 5
    MAXLOCALS = 7

  // access flags 0x11
  public final pingInterval(Ljava/time/Duration;)Lokhttp3/OkHttpClient$Builder;
  @Lorg/codehaus/mojo/animal_sniffer/IgnoreJRERequirement;() // invisible
  @Lorg/jetbrains/annotations/NotNull;() // invisible
    // annotable parameter count: 1 (invisible)
    @Lorg/jetbrains/annotations/NotNull;() // invisible, parameter 0
   L0
    ALOAD 1
    LDC "duration"
    INVOKESTATIC kotlin/jvm/internal/Intrinsics.checkNotNullParameter (Ljava/lang/Object;Ljava/lang/String;)V
   L1
    LINENUMBER 1050 L1
    ALOAD 0
    ASTORE 2
    ALOAD 2
    CHECKCAST okhttp3/OkHttpClient$Builder
    ASTORE 3
   L2
    ICONST_0
    ISTORE 4
   L3
    LINENUMBER 1051 L3
    ALOAD 3
    ALOAD 1
    INVOKEVIRTUAL java/time/Duration.toMillis ()J
    GETSTATIC java/util/concurrent/TimeUnit.MILLISECONDS : Ljava/util/concurrent/TimeUnit;
    INVOKEVIRTUAL okhttp3/OkHttpClient$Builder.pingInterval (JLjava/util/concurrent/TimeUnit;)Lokhttp3/OkHttpClient$Builder;
    POP
   L4
    LINENUMBER 1052 L4
    NOP
   L5
    LINENUMBER 1050 L5
    ALOAD 2
    CHECKCAST okhttp3/OkHttpClient$Builder
   L6
    LINENUMBER 1052 L6
    ARETURN
   L7
    LOCALVARIABLE $i$a$-apply-OkHttpClient$Builder$pingInterval$2 I L3 L5 4
    LOCALVARIABLE $this$pingInterval_u24lambda_u2437 Lokhttp3/OkHttpClient$Builder; L2 L5 3
    LOCALVARIABLE this Lokhttp3/OkHttpClient$Builder; L0 L7 0
    LOCALVARIABLE duration Ljava/time/Duration; L0 L7 1
    MAXSTACK = 4
    MAXLOCALS = 5

  // access flags 0x11
  public final minWebSocketMessageToCompress(J)Lokhttp3/OkHttpClient$Builder;
  @Lorg/jetbrains/annotations/NotNull;() // invisible
   L0
    LINENUMBER 1061 L0
    ALOAD 0
    ASTORE 3
    ALOAD 3
    CHECKCAST okhttp3/OkHttpClient$Builder
    ASTORE 4
   L1
    ICONST_0
    ISTORE 5
   L2
    LINENUMBER 1062 L2
    LLOAD 1
    LCONST_0
    LCMP
    IFLT L3
    ICONST_1
    GOTO L4
   L3
   FRAME FULL [okhttp3/OkHttpClient$Builder J okhttp3/OkHttpClient$Builder okhttp3/OkHttpClient$Builder I] []
    ICONST_0
   L4
   FRAME FULL [okhttp3/OkHttpClient$Builder J okhttp3/OkHttpClient$Builder okhttp3/OkHttpClient$Builder I] [I]
    IFNE L5
    ICONST_0
    ISTORE 6
   L6
    LINENUMBER 1063 L6
    NEW java/lang/StringBuilder
    DUP
    INVOKESPECIAL java/lang/StringBuilder.<init> ()V
    LDC "minWebSocketMessageToCompress must be positive: "
    INVOKEVIRTUAL java/lang/StringBuilder.append (Ljava/lang/String;)Ljava/lang/StringBuilder;
    LLOAD 1
    INVOKEVIRTUAL java/lang/StringBuilder.append (J)Ljava/lang/StringBuilder;
    INVOKEVIRTUAL java/lang/StringBuilder.toString ()Ljava/lang/String;
   L7
    LINENUMBER 1062 L7
    ASTORE 6
    NEW java/lang/IllegalArgumentException
    DUP
    ALOAD 6
    INVOKEVIRTUAL java/lang/Object.toString ()Ljava/lang/String;
    INVOKESPECIAL java/lang/IllegalArgumentException.<init> (Ljava/lang/String;)V
    ATHROW
   L5
    LINENUMBER 1066 L5
   FRAME FULL [okhttp3/OkHttpClient$Builder J okhttp3/OkHttpClient$Builder okhttp3/OkHttpClient$Builder I] []
    ALOAD 4
    LLOAD 1
    PUTFIELD okhttp3/OkHttpClient$Builder.minWebSocketMessageToCompress : J
   L8
    LINENUMBER 1067 L8
    NOP
   L9
    LINENUMBER 1061 L9
    ALOAD 3
    CHECKCAST okhttp3/OkHttpClient$Builder
   L10
    LINENUMBER 1067 L10
    ARETURN
   L11
    LOCALVARIABLE $i$a$-require-OkHttpClient$Builder$minWebSocketMessageToCompress$1$1 I L6 L7 6
    LOCALVARIABLE $i$a$-apply-OkHttpClient$Builder$minWebSocketMessageToCompress$1 I L2 L9 5
    LOCALVARIABLE $this$minWebSocketMessageToCompress_u24lambda_u2439 Lokhttp3/OkHttpClient$Builder; L1 L9 4
    LOCALVARIABLE this Lokhttp3/OkHttpClient$Builder; L0 L11 0
    LOCALVARIABLE bytes J L0 L11 1
    MAXSTACK = 4
    MAXLOCALS = 7

  // access flags 0x11
  public final build()Lokhttp3/OkHttpClient;
  @Lorg/jetbrains/annotations/NotNull;() // invisible
    ALOAD 0
    INVOKESTATIC io/embrace/android/embracesdk/okhttp3/swazzle/callback/okhttp3/OkHttpClient$Builder._preBuild (Lokhttp3/OkHttpClient$Builder;)V
   L0
    LINENUMBER 1069 L0
    NEW okhttp3/OkHttpClient
    DUP
    ALOAD 0
    INVOKESPECIAL okhttp3/OkHttpClient.<init> (Lokhttp3/OkHttpClient$Builder;)V
    ARETURN
   L1
    LOCALVARIABLE this Lokhttp3/OkHttpClient$Builder; L0 L1 0
    MAXSTACK = 3
    MAXLOCALS = 1
}
