// class version 55.0 (55)
// access flags 0x21
public class io/embrace/test/fixtures/JavaLambdaOnClickListener extends androidx/fragment/app/Fragment {

  // compiled from: JavaLambdaOnClickListener.java
  // access flags 0x609
  public static abstract INNERCLASS android/view/View$OnClickListener android/view/View OnClickListener
  // access flags 0x19
  public final static INNERCLASS java/lang/invoke/MethodHandles$Lookup java/lang/invoke/MethodHandles Lookup

  // access flags 0x1
  public <init>()V
   L0
    LINENUMBER 15 L0
    ALOAD 0
    INVOKESPECIAL androidx/fragment/app/Fragment.<init> ()V
    RETURN
   L1
    LOCALVARIABLE this Lio/embrace/test/fixtures/JavaLambdaOnClickListener; L0 L1 0
    MAXSTACK = 1
    MAXLOCALS = 1

  // access flags 0x1
  public onCreateView(Landroid/view/LayoutInflater;Landroid/view/ViewGroup;Landroid/os/Bundle;)Landroid/view/View;
    // annotable parameter count: 3 (invisible)
    @Landroidx/annotation/NonNull;() // invisible, parameter 0
   L0
    LINENUMBER 19 L0
    ALOAD 0
    ALOAD 1
    ALOAD 2
    ALOAD 3
    INVOKESPECIAL androidx/fragment/app/Fragment.onCreateView (Landroid/view/LayoutInflater;Landroid/view/ViewGroup;Landroid/os/Bundle;)Landroid/view/View;
    ASTORE 4
   L1
    LINENUMBER 20 L1
    ALOAD 4
    IFNULL L2
   L3
    LINENUMBER 21 L3
    ALOAD 4
    INVOKEDYNAMIC onClick()Landroid/view/View$OnClickListener; [
      // handle kind 0x6 : INVOKESTATIC
      java/lang/invoke/LambdaMetafactory.metafactory(Ljava/lang/invoke/MethodHandles$Lookup;Ljava/lang/String;Ljava/lang/invoke/MethodType;Ljava/lang/invoke/MethodType;Ljava/lang/invoke/MethodHandle;Ljava/lang/invoke/MethodType;)Ljava/lang/invoke/CallSite;
      // arguments:
      (Landroid/view/View;)V,
      // handle kind 0x6 : INVOKESTATIC
      io/embrace/test/fixtures/JavaLambdaOnClickListener.lambda$onCreateView$0(Landroid/view/View;)V,
      (Landroid/view/View;)V
    ]
    INVOKEVIRTUAL android/view/View.setOnClickListener (Landroid/view/View$OnClickListener;)V
   L2
    LINENUMBER 25 L2
   FRAME FULL [io/embrace/test/fixtures/JavaLambdaOnClickListener android/view/LayoutInflater android/view/ViewGroup android/os/Bundle android/view/View] []
    ALOAD 4
    ARETURN
   L4
    LOCALVARIABLE this Lio/embrace/test/fixtures/JavaLambdaOnClickListener; L0 L4 0
    LOCALVARIABLE inflater Landroid/view/LayoutInflater; L0 L4 1
    LOCALVARIABLE container Landroid/view/ViewGroup; L0 L4 2
    LOCALVARIABLE savedInstanceState Landroid/os/Bundle; L0 L4 3
    LOCALVARIABLE view Landroid/view/View; L1 L4 4
    MAXSTACK = 4
    MAXLOCALS = 5

  // access flags 0x100A
  private static synthetic lambda$onCreateView$0(Landroid/view/View;)V
    ACONST_NULL
    ALOAD 0
    INVOKESTATIC io/embrace/android/embracesdk/ViewSwazzledHooks$OnClickListener._preOnClick (Landroid/view/View$OnClickListener;Landroid/view/View;)V
   L0
    LINENUMBER 22 L0
    LDC "Embrace"
    LDC "test"
    INVOKESTATIC android/util/Log.d (Ljava/lang/String;Ljava/lang/String;)I
    POP
   L1
    LINENUMBER 23 L1
    RETURN
   L2
    LOCALVARIABLE lambdaView Landroid/view/View; L0 L2 0
    MAXSTACK = 2
    MAXLOCALS = 1
}
