// class version 55.0 (55)
// access flags 0x31
public final class io/embrace/test/fixtures/TargetMethodEndVisitorObj {

  // compiled from: TargetMethodEndVisitorObj.kt

  @Lkotlin/Metadata;(mv={2, 0, 0}, k=1, xi=48, d1={"\u0000\u0014\n\u0002\u0018\u0002\n\u0002\u0010\u0000\n\u0002\u0008\u0003\n\u0002\u0010\u0002\n\u0002\u0008\u0004\u0018\u00002\u00020\u0001B\u0007\u00a2\u0006\u0004\u0008\u0002\u0010\u0003J\u0006\u0010\u0004\u001a\u00020\u0005J\u0006\u0010\u0006\u001a\u00020\u0005J\u0006\u0010\u0007\u001a\u00020\u0005J\u0006\u0010\u0008\u001a\u00020\u0005\u00a8\u0006\u0009"}, d2={"Lio/embrace/test/fixtures/TargetMethodEndVisitorObj;", "", "<init>", "()V", "instrumentAtEndWithReturn", "", "instrumentAtEndWithoutReturn", "instrumentAtEndWithThrow", "instrumentAtEndWithMultipleReturns", "embrace-bytecode-instrumentation-tests"})
  // access flags 0x19
  public final static INNERCLASS kotlin/random/Random$Default kotlin/random/Random Default

  // access flags 0x1
  public <init>()V
   L0
    LINENUMBER 5 L0
    ALOAD 0
    INVOKESPECIAL java/lang/Object.<init> ()V
    RETURN
   L1
    LOCALVARIABLE this Lio/embrace/test/fixtures/TargetMethodEndVisitorObj; L0 L1 0
    MAXSTACK = 1
    MAXLOCALS = 1

  // access flags 0x11
  public final instrumentAtEndWithReturn()V
   L0
    LINENUMBER 8 L0
    LDC "Instrumenting at the end of a method with a return statement"
    GETSTATIC java/lang/System.out : Ljava/io/PrintStream;
    SWAP
    INVOKEVIRTUAL java/io/PrintStream.print (Ljava/lang/Object;)V
   L1
    LINENUMBER 9 L1
    INVOKESTATIC io/embrace/gradle/plugin/instrumentation/InjectedClass.injectedMethod ()V
    RETURN
   L2
    LOCALVARIABLE this Lio/embrace/test/fixtures/TargetMethodEndVisitorObj; L0 L2 0
    MAXSTACK = 2
    MAXLOCALS = 1

  // access flags 0x11
  public final instrumentAtEndWithoutReturn()V
   L0
    LINENUMBER 13 L0
    LDC "Instrumenting at the end of a method without a return statement"
    GETSTATIC java/lang/System.out : Ljava/io/PrintStream;
    SWAP
    INVOKEVIRTUAL java/io/PrintStream.print (Ljava/lang/Object;)V
   L1
    LINENUMBER 14 L1
    INVOKESTATIC io/embrace/gradle/plugin/instrumentation/InjectedClass.injectedMethod ()V
    RETURN
   L2
    LOCALVARIABLE this Lio/embrace/test/fixtures/TargetMethodEndVisitorObj; L0 L2 0
    MAXSTACK = 2
    MAXLOCALS = 1

  // access flags 0x11
  public final instrumentAtEndWithThrow()V
   L0
    LINENUMBER 17 L0
    LDC "Instrumenting at the end of a method with a throw statement"
    GETSTATIC java/lang/System.out : Ljava/io/PrintStream;
    SWAP
    INVOKEVIRTUAL java/io/PrintStream.print (Ljava/lang/Object;)V
   L1
    LINENUMBER 18 L1
    NEW java/lang/Exception
    DUP
    LDC "Exception"
    INVOKESPECIAL java/lang/Exception.<init> (Ljava/lang/String;)V
    INVOKESTATIC io/embrace/gradle/plugin/instrumentation/InjectedClass.injectedMethod ()V
    ATHROW
   L2
    LOCALVARIABLE this Lio/embrace/test/fixtures/TargetMethodEndVisitorObj; L0 L2 0
    MAXSTACK = 3
    MAXLOCALS = 1

  // access flags 0x11
  public final instrumentAtEndWithMultipleReturns()V
   L0
    LINENUMBER 22 L0
    GETSTATIC kotlin/random/Random.Default : Lkotlin/random/Random$Default;
    INVOKEVIRTUAL kotlin/random/Random$Default.nextBoolean ()Z
    IFEQ L1
   L2
    LINENUMBER 23 L2
    LDC "Instrumenting at the end of a method with multiple return statements - first return"
    GETSTATIC java/lang/System.out : Ljava/io/PrintStream;
    SWAP
    INVOKEVIRTUAL java/io/PrintStream.print (Ljava/lang/Object;)V
   L3
    LINENUMBER 24 L3
    INVOKESTATIC io/embrace/gradle/plugin/instrumentation/InjectedClass.injectedMethod ()V
    RETURN
   L1
    LINENUMBER 26 L1
   FRAME FULL [io/embrace/test/fixtures/TargetMethodEndVisitorObj] []
    LDC "Instrumenting at the end of a method with multiple return statements - second return"
    GETSTATIC java/lang/System.out : Ljava/io/PrintStream;
    SWAP
    INVOKEVIRTUAL java/io/PrintStream.print (Ljava/lang/Object;)V
   L4
    LINENUMBER 27 L4
    INVOKESTATIC io/embrace/gradle/plugin/instrumentation/InjectedClass.injectedMethod ()V
    RETURN
   L5
    LOCALVARIABLE this Lio/embrace/test/fixtures/TargetMethodEndVisitorObj; L0 L5 0
    MAXSTACK = 2
    MAXLOCALS = 1
}
